[{"id": 9619441, "course_id": 22100, "map_id": 221, "map_name": "bkz_underground_crypt_v3", "map_stage": 0, "stage_tier": 5, "steam_id": "STEAM_1:0:182656610", "player_name": "smieszneznaczki", "mode": "kz_timer", "time": 693.813, "teleports": 0, "created_on": "2020-12-23T12:02:40Z", "points": 10000}, {"id": 22591885, "course_id": 22100, "map_id": 221, "map_name": "bkz_underground_crypt_v3", "map_stage": 0, "stage_tier": 5, "steam_id": "STEAM_1:0:90225250", "player_name": "sage :D", "mode": "kz_timer", "time": 709.586, "teleports": 0, "created_on": "2023-08-09T22:35:02Z", "points": 9934}, {"id": 8774621, "course_id": 22100, "map_id": 221, "map_name": "bkz_underground_crypt_v3", "map_stage": 0, "stage_tier": 5, "steam_id": "STEAM_1:1:122301121", "player_name": "Kuupo", "mode": "kz_timer", "time": 779.75, "teleports": 0, "created_on": "2020-10-28T21:42:35Z", "points": 9885}, {"id": 4419622, "course_id": 22100, "map_id": 221, "map_name": "bkz_underground_crypt_v3", "map_stage": 0, "stage_tier": 5, "steam_id": "STEAM_1:0:71375927", "player_name": "Shard", "mode": "kz_timer", "time": 796.047, "teleports": 0, "created_on": "2019-12-19T16:01:23Z", "points": 9847}, {"id": 15783461, "course_id": 22100, "map_id": 221, "map_name": "bkz_underground_crypt_v3", "map_stage": 0, "stage_tier": 5, "steam_id": "STEAM_1:1:91469801", "player_name": "cia :D", "mode": "kz_timer", "time": 824.07, "teleports": 0, "created_on": "2022-03-21T02:00:16Z", "points": 9798}, {"id": 4140867, "course_id": 22100, "map_id": 221, "map_name": "bkz_underground_crypt_v3", "map_stage": 0, "stage_tier": 5, "steam_id": "STEAM_1:0:122816464", "player_name": "GiimPy", "mode": "kz_timer", "time": 824.156, "teleports": 0, "created_on": "2019-11-13T17:12:48Z", "points": 9770}, {"id": 20373055, "course_id": 22100, "map_id": 221, "map_name": "bkz_underground_crypt_v3", "map_stage": 0, "stage_tier": 5, "steam_id": "STEAM_1:1:91208527", "player_name": "Fksch", "mode": "kz_timer", "time": 827.695, "teleports": 0, "created_on": "2023-03-25T17:18:48Z", "points": 9737}, {"id": 16951943, "course_id": 22100, "map_id": 221, "map_name": "bkz_underground_crypt_v3", "map_stage": 0, "stage_tier": 5, "steam_id": "STEAM_1:0:27080650", "player_name": "pezizz", "mode": "kz_timer", "time": 841.781, "teleports": 0, "created_on": "2022-06-22T22:35:28Z", "points": 9717}, {"id": 3691463, "course_id": 22100, "map_id": 221, "map_name": "bkz_underground_crypt_v3", "map_stage": 0, "stage_tier": 5, "steam_id": "STEAM_1:1:23960079", "player_name": "LEWLY", "mode": "kz_timer", "time": 882.319, "teleports": 0, "created_on": "2019-09-12T19:52:06Z", "points": 9670}, {"id": 20370090, "course_id": 22100, "map_id": 221, "map_name": "bkz_underground_crypt_v3", "map_stage": 0, "stage_tier": 5, "steam_id": "STEAM_1:1:118898580", "player_name": "Dima", "mode": "kz_timer", "time": 903.109, "teleports": 0, "created_on": "2023-03-25T14:41:21Z", "points": 9582}, {"id": 11626629, "course_id": 22100, "map_id": 221, "map_name": "bkz_underground_crypt_v3", "map_stage": 0, "stage_tier": 5, "steam_id": "STEAM_1:0:142574868", "player_name": "TrickZ", "mode": "kz_timer", "time": 907.313, "teleports": 0, "created_on": "2021-04-11T16:31:16Z", "points": 9564}, {"id": 4426135, "course_id": 22100, "map_id": 221, "map_name": "bkz_underground_crypt_v3", "map_stage": 0, "stage_tier": 5, "steam_id": "STEAM_1:1:66714060", "player_name": "sumpy", "mode": "kz_timer", "time": 912.125, "teleports": 0, "created_on": "2019-12-20T19:24:09Z", "points": 9546}, {"id": 20369545, "course_id": 22100, "map_id": 221, "map_name": "bkz_underground_crypt_v3", "map_stage": 0, "stage_tier": 5, "steam_id": "STEAM_1:1:11621314", "player_name": "-}{0}{0JI_SLaYeR-", "mode": "kz_timer", "time": 917.695, "teleports": 0, "created_on": "2023-03-25T14:14:48Z", "points": 9528}, {"id": 7139861, "course_id": 22100, "map_id": 221, "map_name": "bkz_underground_crypt_v3", "map_stage": 0, "stage_tier": 5, "steam_id": "STEAM_1:0:835149", "player_name": "trauma", "mode": "kz_timer", "time": 926.125, "teleports": 0, "created_on": "2020-07-16T04:17:35Z", "points": 9492}, {"id": 7444902, "course_id": 22100, "map_id": 221, "map_name": "bkz_underground_crypt_v3", "map_stage": 0, "stage_tier": 5, "steam_id": "STEAM_1:0:98547634", "player_name": "Xeno", "mode": "kz_timer", "time": 926.594, "teleports": 0, "created_on": "2020-08-04T14:42:53Z", "points": 9486}, {"id": 15027771, "course_id": 22100, "map_id": 221, "map_name": "bkz_underground_crypt_v3", "map_stage": 0, "stage_tier": 5, "steam_id": "STEAM_1:1:6716268", "player_name": "\u771f\u591c\u4e2d\u306e\u30c9\u30a2", "mode": "kz_timer", "time": 930.297, "teleports": 0, "created_on": "2022-01-20T19:10:57Z", "points": 9484}, {"id": 8387417, "course_id": 22100, "map_id": 221, "map_name": "bkz_underground_crypt_v3", "map_stage": 0, "stage_tier": 5, "steam_id": "STEAM_1:1:26097265", "player_name": "topo-", "mode": "kz_timer", "time": 934.18, "teleports": 0, "created_on": "2020-10-01T01:41:16Z", "points": 9482}, {"id": 9704489, "course_id": 22100, "map_id": 221, "map_name": "bkz_underground_crypt_v3", "map_stage": 0, "stage_tier": 5, "steam_id": "STEAM_1:0:115804973", "player_name": "Samuel", "mode": "kz_timer", "time": 940.531, "teleports": 0, "created_on": "2020-12-28T13:55:30Z", "points": 9472}, {"id": 4390320, "course_id": 22100, "map_id": 221, "map_name": "bkz_underground_crypt_v3", "map_stage": 0, "stage_tier": 5, "steam_id": "STEAM_1:0:79208088", "player_name": "zer0.k", "mode": "kz_timer", "time": 948.906, "teleports": 0, "created_on": "2019-12-15T22:43:59Z", "points": 9461}, {"id": 8924376, "course_id": 22100, "map_id": 221, "map_name": "bkz_underground_crypt_v3", "map_stage": 0, "stage_tier": 5, "steam_id": "STEAM_1:1:497395759", "player_name": "pogo", "mode": "kz_timer", "time": 950.953, "teleports": 0, "created_on": "2020-11-07T22:23:06Z", "points": 9460}, {"id": 1983782, "course_id": 22100, "map_id": 221, "map_name": "bkz_underground_crypt_v3", "map_stage": 0, "stage_tier": 5, "steam_id": "STEAM_1:1:27112765", "player_name": "nykaN", "mode": "kz_timer", "time": 966.777, "teleports": 0, "created_on": "2019-02-02T18:34:35Z", "points": 9435}, {"id": 4051636, "course_id": 22100, "map_id": 221, "map_name": "bkz_underground_crypt_v3", "map_stage": 0, "stage_tier": 5, "steam_id": "STEAM_1:0:103429899", "player_name": "JJ", "mode": "kz_timer", "time": 970.469, "teleports": 0, "created_on": "2019-11-02T19:55:14Z", "points": 9429}, {"id": 8490841, "course_id": 22100, "map_id": 221, "map_name": "bkz_underground_crypt_v3", "map_stage": 0, "stage_tier": 5, "steam_id": "STEAM_1:1:128389518", "player_name": "Exusiai", "mode": "kz_timer", "time": 974.93, "teleports": 0, "created_on": "2020-10-08T06:59:56Z", "points": 9423}, {"id": 5519889, "course_id": 22100, "map_id": 221, "map_name": "bkz_underground_crypt_v3", "map_stage": 0, "stage_tier": 5, "steam_id": "STEAM_1:0:55972459", "player_name": "Fafnir", "mode": "kz_timer", "time": 988.797, "teleports": 0, "created_on": "2020-03-29T07:22:49Z", "points": 9408}, {"id": 7816100, "course_id": 22100, "map_id": 221, "map_name": "bkz_underground_crypt_v3", "map_stage": 0, "stage_tier": 5, "steam_id": "STEAM_1:1:51653737", "player_name": "alves", "mode": "kz_timer", "time": 998.354, "teleports": 0, "created_on": "2020-08-27T02:51:43Z", "points": 9399}, {"id": 5796, "course_id": 22100, "map_id": 221, "map_name": "bkz_underground_crypt_v3", "map_stage": 0, "stage_tier": 5, "steam_id": "STEAM_1:1:46574979", "player_name": "ZoSo", "mode": "kz_timer", "time": 1010.97, "teleports": 0, "created_on": "2016-09-24T17:52:38Z", "points": 9384}, {"id": 11538280, "course_id": 22100, "map_id": 221, "map_name": "bkz_underground_crypt_v3", "map_stage": 0, "stage_tier": 5, "steam_id": "STEAM_1:1:17676543", "player_name": "Gurylla", "mode": "kz_timer", "time": 1014.68, "teleports": 0, "created_on": "2021-04-06T23:25:07Z", "points": 9381}, {"id": 17928664, "course_id": 22100, "map_id": 221, "map_name": "bkz_underground_crypt_v3", "map_stage": 0, "stage_tier": 5, "steam_id": "STEAM_1:1:94938745", "player_name": "nuts *:\uff65\uff9f\u2727(\ua20d\u1d17\ua20d)\u2727", "mode": "kz_timer", "time": 1019.547, "teleports": 0, "created_on": "2022-09-01T17:43:27Z", "points": 9375}, {"id": 8471696, "course_id": 22100, "map_id": 221, "map_name": "bkz_underground_crypt_v3", "map_stage": 0, "stage_tier": 5, "steam_id": "STEAM_1:1:51660477", "player_name": "vmi", "mode": "kz_timer", "time": 1023.789, "teleports": 0, "created_on": "2020-10-06T20:14:16Z", "points": 9368}, {"id": 9707592, "course_id": 22100, "map_id": 221, "map_name": "bkz_underground_crypt_v3", "map_stage": 0, "stage_tier": 5, "steam_id": "STEAM_1:1:203024318", "player_name": "a", "mode": "kz_timer", "time": 1034.414, "teleports": 0, "created_on": "2020-12-28T17:00:02Z", "points": 9354}, {"id": 18178370, "course_id": 22100, "map_id": 221, "map_name": "bkz_underground_crypt_v3", "map_stage": 0, "stage_tier": 5, "steam_id": "STEAM_1:0:144015727", "player_name": "Nessie", "mode": "kz_timer", "time": 1052.461, "teleports": 0, "created_on": "2022-09-19T04:23:42Z", "points": 9316}, {"id": 22592068, "course_id": 22100, "map_id": 221, "map_name": "bkz_underground_crypt_v3", "map_stage": 0, "stage_tier": 5, "steam_id": "STEAM_1:1:157151507", "player_name": "katie", "mode": "kz_timer", "time": 1067.766, "teleports": 0, "created_on": "2023-08-09T23:13:27Z", "points": 9285}, {"id": 4038566, "course_id": 22100, "map_id": 221, "map_name": "bkz_underground_crypt_v3", "map_stage": 0, "stage_tier": 5, "steam_id": "STEAM_1:1:11374239", "player_name": "Zach47", "mode": "kz_timer", "time": 1070.094, "teleports": 0, "created_on": "2019-11-01T07:30:37Z", "points": 9276}, {"id": 1237518, "course_id": 22100, "map_id": 221, "map_name": "bkz_underground_crypt_v3", "map_stage": 0, "stage_tier": 5, "steam_id": "STEAM_1:0:182948977", "player_name": "slick", "mode": "kz_timer", "time": 1076.086, "teleports": 0, "created_on": "2018-10-03T17:54:28Z", "points": 9265}, {"id": 17850801, "course_id": 22100, "map_id": 221, "map_name": "bkz_underground_crypt_v3", "map_stage": 0, "stage_tier": 5, "steam_id": "STEAM_1:1:218963888", "player_name": "chemy:v", "mode": "kz_timer", "time": 1089.703, "teleports": 0, "created_on": "2022-08-27T14:14:56Z", "points": 9251}, {"id": 6305117, "course_id": 22100, "map_id": 221, "map_name": "bkz_underground_crypt_v3", "map_stage": 0, "stage_tier": 5, "steam_id": "STEAM_1:1:90377113", "player_name": "CMJ", "mode": "kz_timer", "time": 1091.242, "teleports": 0, "created_on": "2020-05-17T22:17:26Z", "points": 9249}, {"id": 11051971, "course_id": 22100, "map_id": 221, "map_name": "bkz_underground_crypt_v3", "map_stage": 0, "stage_tier": 5, "steam_id": "STEAM_1:0:29122831", "player_name": "Boux", "mode": "kz_timer", "time": 1097.234, "teleports": 0, "created_on": "2021-03-12T03:37:00Z", "points": 9241}, {"id": 13127872, "course_id": 22100, "map_id": 221, "map_name": "bkz_underground_crypt_v3", "map_stage": 0, "stage_tier": 5, "steam_id": "STEAM_1:0:20502582", "player_name": "Billy Joel", "mode": "kz_timer", "time": 1099.961, "teleports": 0, "created_on": "2021-07-30T08:32:23Z", "points": 9233}, {"id": 1422828, "course_id": 22100, "map_id": 221, "map_name": "bkz_underground_crypt_v3", "map_stage": 0, "stage_tier": 5, "steam_id": "STEAM_1:0:93814773", "player_name": "\u00af\\_(\u30c4)_/\u00af", "mode": "kz_timer", "time": 1104.242, "teleports": 0, "created_on": "2018-11-07T09:18:26Z", "points": 9226}, {"id": 3928, "course_id": 22100, "map_id": 221, "map_name": "bkz_underground_crypt_v3", "map_stage": 0, "stage_tier": 5, "steam_id": "STEAM_1:1:11972563", "player_name": "b0utamine", "mode": "kz_timer", "time": 1105.98, "teleports": 0, "created_on": "2016-06-17T20:17:14Z", "points": 9224}, {"id": 7270993, "course_id": 22100, "map_id": 221, "map_name": "bkz_underground_crypt_v3", "map_stage": 0, "stage_tier": 5, "steam_id": "STEAM_1:0:37243285", "player_name": "lynch", "mode": "kz_timer", "time": 1125.355, "teleports": 0, "created_on": "2020-07-24T19:25:12Z", "points": 9201}, {"id": 1951756, "course_id": 22100, "map_id": 221, "map_name": "bkz_underground_crypt_v3", "map_stage": 0, "stage_tier": 5, "steam_id": "STEAM_1:1:66195921", "player_name": "\u2714\u0110\u00fbb\u0160\u0167\u0119p GENERAL \u00c7\u014c\u00c7\u0104\u012e\u0145\u0118\u2714", "mode": "kz_timer", "time": 1125.358, "teleports": 0, "created_on": "2019-01-29T15:19:12Z", "points": 9198}, {"id": 3005429, "course_id": 22100, "map_id": 221, "map_name": "bkz_underground_crypt_v3", "map_stage": 0, "stage_tier": 5, "steam_id": "STEAM_1:0:33286647", "player_name": "dva's feet", "mode": "kz_timer", "time": 1125.805, "teleports": 0, "created_on": "2019-06-06T16:41:21Z", "points": 9197}, {"id": 1238552, "course_id": 22100, "map_id": 221, "map_name": "bkz_underground_crypt_v3", "map_stage": 0, "stage_tier": 5, "steam_id": "STEAM_1:1:45421221", "player_name": "Jak", "mode": "kz_timer", "time": 1153.938, "teleports": 0, "created_on": "2018-10-03T21:56:45Z", "points": 9152}, {"id": 3688551, "course_id": 22100, "map_id": 221, "map_name": "bkz_underground_crypt_v3", "map_stage": 0, "stage_tier": 5, "steam_id": "STEAM_1:0:49617951", "player_name": "doorknob enthusiast", "mode": "kz_timer", "time": 1159.813, "teleports": 0, "created_on": "2019-09-12T09:22:58Z", "points": 9144}, {"id": 4721, "course_id": 22100, "map_id": 221, "map_name": "bkz_underground_crypt_v3", "map_stage": 0, "stage_tier": 5, "steam_id": "STEAM_1:1:19210276", "player_name": "Porkkana1337", "mode": "kz_timer", "time": 1162.98, "teleports": 0, "created_on": "2017-05-27T11:26:31Z", "points": 9140}, {"id": 16832639, "course_id": 22100, "map_id": 221, "map_name": "bkz_underground_crypt_v3", "map_stage": 0, "stage_tier": 5, "steam_id": "STEAM_1:0:29858116", "player_name": "FK Petas", "mode": "kz_timer", "time": 1204.508, "teleports": 0, "created_on": "2022-06-13T15:42:39Z", "points": 9080}, {"id": 13022969, "course_id": 22100, "map_id": 221, "map_name": "bkz_underground_crypt_v3", "map_stage": 0, "stage_tier": 5, "steam_id": "STEAM_1:0:49643435", "player_name": "isshiki", "mode": "kz_timer", "time": 1208.125, "teleports": 0, "created_on": "2021-07-21T14:53:24Z", "points": 9074}, {"id": 4145446, "course_id": 22100, "map_id": 221, "map_name": "bkz_underground_crypt_v3", "map_stage": 0, "stage_tier": 5, "steam_id": "STEAM_1:0:225263168", "player_name": "mousan", "mode": "kz_timer", "time": 1220.281, "teleports": 0, "created_on": "2019-11-14T06:51:00Z", "points": 9045}, {"id": 21123296, "course_id": 22100, "map_id": 221, "map_name": "bkz_underground_crypt_v3", "map_stage": 0, "stage_tier": 5, "steam_id": "STEAM_1:1:58874509", "player_name": "iBUYFL0WER Burgit", "mode": "kz_timer", "time": 1223.98, "teleports": 0, "created_on": "2023-05-05T13:22:20Z", "points": 9035}, {"id": 8248045, "course_id": 22100, "map_id": 221, "map_name": "bkz_underground_crypt_v3", "map_stage": 0, "stage_tier": 5, "steam_id": "STEAM_1:0:142871078", "player_name": "3 fortnite vbucks", "mode": "kz_timer", "time": 1238.688, "teleports": 0, "created_on": "2020-09-21T14:25:54Z", "points": 9004}, {"id": 1024309, "course_id": 22100, "map_id": 221, "map_name": "bkz_underground_crypt_v3", "map_stage": 0, "stage_tier": 5, "steam_id": "STEAM_1:1:180456952", "player_name": "Ricky", "mode": "kz_timer", "time": 1242.313, "teleports": 0, "created_on": "2018-08-26T23:13:02Z", "points": 8994}, {"id": 20367777, "course_id": 22100, "map_id": 221, "map_name": "bkz_underground_crypt_v3", "map_stage": 0, "stage_tier": 5, "steam_id": "STEAM_1:0:178573631", "player_name": "AyayaBoy :D", "mode": "kz_timer", "time": 1250.953, "teleports": 0, "created_on": "2023-03-25T12:24:44Z", "points": 8978}, {"id": 2838048, "course_id": 22100, "map_id": 221, "map_name": "bkz_underground_crypt_v3", "map_stage": 0, "stage_tier": 5, "steam_id": "STEAM_1:0:96586644", "player_name": "JAK619", "mode": "kz_timer", "time": 1254.328, "teleports": 0, "created_on": "2019-05-17T16:00:38Z", "points": 8971}, {"id": 18566809, "course_id": 22100, "map_id": 221, "map_name": "bkz_underground_crypt_v3", "map_stage": 0, "stage_tier": 5, "steam_id": "STEAM_1:1:41462578", "player_name": "ooppppp", "mode": "kz_timer", "time": 1255.219, "teleports": 0, "created_on": "2022-10-19T00:06:30Z", "points": 8970}, {"id": 3482713, "course_id": 22100, "map_id": 221, "map_name": "bkz_underground_crypt_v3", "map_stage": 0, "stage_tier": 5, "steam_id": "STEAM_1:1:9836467", "player_name": "Charon", "mode": "kz_timer", "time": 1263.585, "teleports": 0, "created_on": "2019-08-12T04:24:20Z", "points": 8957}, {"id": 7180991, "course_id": 22100, "map_id": 221, "map_name": "bkz_underground_crypt_v3", "map_stage": 0, "stage_tier": 5, "steam_id": "STEAM_1:0:48560187", "player_name": "mattiS", "mode": "kz_timer", "time": 1268.561, "teleports": 0, "created_on": "2020-07-18T21:37:49Z", "points": 8951}, {"id": 12766221, "course_id": 22100, "map_id": 221, "map_name": "bkz_underground_crypt_v3", "map_stage": 0, "stage_tier": 5, "steam_id": "STEAM_1:0:187057880", "player_name": "zeo", "mode": "kz_timer", "time": 1273.309, "teleports": 0, "created_on": "2021-06-23T22:08:31Z", "points": 8945}, {"id": 5985, "course_id": 22100, "map_id": 221, "map_name": "bkz_underground_crypt_v3", "map_stage": 0, "stage_tier": 5, "steam_id": "STEAM_1:1:49540815", "player_name": "dedi", "mode": "kz_timer", "time": 1294.67, "teleports": 0, "created_on": "2016-09-15T04:48:37Z", "points": 8917}, {"id": 3949840, "course_id": 22100, "map_id": 221, "map_name": "bkz_underground_crypt_v3", "map_stage": 0, "stage_tier": 5, "steam_id": "STEAM_1:1:40874265", "player_name": "nickely", "mode": "kz_timer", "time": 1329.758, "teleports": 0, "created_on": "2019-10-21T00:51:57Z", "points": 8871}, {"id": 14017766, "course_id": 22100, "map_id": 221, "map_name": "bkz_underground_crypt_v3", "map_stage": 0, "stage_tier": 5, "steam_id": "STEAM_1:1:97984616", "player_name": "spaghetti senpai", "mode": "kz_timer", "time": 1334.002, "teleports": 0, "created_on": "2021-10-15T22:46:44Z", "points": 8865}, {"id": 16616215, "course_id": 22100, "map_id": 221, "map_name": "bkz_underground_crypt_v3", "map_stage": 0, "stage_tier": 5, "steam_id": "STEAM_1:1:64300257", "player_name": "das kindershredder", "mode": "kz_timer", "time": 1335.578, "teleports": 0, "created_on": "2022-05-27T12:17:43Z", "points": 8863}, {"id": 20093235, "course_id": 22100, "map_id": 221, "map_name": "bkz_underground_crypt_v3", "map_stage": 0, "stage_tier": 5, "steam_id": "STEAM_1:1:196861182", "player_name": "puff.", "mode": "kz_timer", "time": 1339.383, "teleports": 0, "created_on": "2023-03-09T03:49:26Z", "points": 8859}, {"id": 20136959, "course_id": 22100, "map_id": 221, "map_name": "bkz_underground_crypt_v3", "map_stage": 0, "stage_tier": 5, "steam_id": "STEAM_1:1:605441756", "player_name": "991ts", "mode": "kz_timer", "time": 1348.656, "teleports": 0, "created_on": "2023-03-11T15:19:04Z", "points": 8845}, {"id": 3178, "course_id": 22100, "map_id": 221, "map_name": "bkz_underground_crypt_v3", "map_stage": 0, "stage_tier": 5, "steam_id": "STEAM_1:0:84690156", "player_name": "tricky", "mode": "kz_timer", "time": 1349.95, "teleports": 0, "created_on": "2016-11-30T03:49:42Z", "points": 8844}, {"id": 4589, "course_id": 22100, "map_id": 221, "map_name": "bkz_underground_crypt_v3", "map_stage": 0, "stage_tier": 5, "steam_id": "STEAM_1:1:17160289", "player_name": "MachineChaos", "mode": "kz_timer", "time": 1355.94, "teleports": 0, "created_on": "2017-12-17T21:41:49Z", "points": 8836}, {"id": 11615983, "course_id": 22100, "map_id": 221, "map_name": "bkz_underground_crypt_v3", "map_stage": 0, "stage_tier": 5, "steam_id": "STEAM_1:1:165021693", "player_name": "soak", "mode": "kz_timer", "time": 1360.719, "teleports": 0, "created_on": "2021-04-11T03:43:53Z", "points": 8830}, {"id": 6727, "course_id": 22100, "map_id": 221, "map_name": "bkz_underground_crypt_v3", "map_stage": 0, "stage_tier": 5, "steam_id": "STEAM_1:1:5946194", "player_name": "KELLZ", "mode": "kz_timer", "time": 1367.39, "teleports": 0, "created_on": "2016-03-06T17:33:31Z", "points": 8820}, {"id": 4626706, "course_id": 22100, "map_id": 221, "map_name": "bkz_underground_crypt_v3", "map_stage": 0, "stage_tier": 5, "steam_id": "STEAM_1:0:112360279", "player_name": "Aivu Summu", "mode": "kz_timer", "time": 1367.594, "teleports": 0, "created_on": "2020-01-12T19:21:21Z", "points": 8819}, {"id": 19817572, "course_id": 22100, "map_id": 221, "map_name": "bkz_underground_crypt_v3", "map_stage": 0, "stage_tier": 5, "steam_id": "STEAM_1:0:10273487", "player_name": "Rolla", "mode": "kz_timer", "time": 1376.664, "teleports": 0, "created_on": "2023-02-02T15:03:02Z", "points": 8805}, {"id": 8387527, "course_id": 22100, "map_id": 221, "map_name": "bkz_underground_crypt_v3", "map_stage": 0, "stage_tier": 5, "steam_id": "STEAM_1:0:171380896", "player_name": "Anq", "mode": "kz_timer", "time": 1380.469, "teleports": 0, "created_on": "2020-10-01T01:54:22Z", "points": 8801}, {"id": 6076, "course_id": 22100, "map_id": 221, "map_name": "bkz_underground_crypt_v3", "map_stage": 0, "stage_tier": 5, "steam_id": "STEAM_1:1:49543244", "player_name": "break", "mode": "kz_timer", "time": 1383.68, "teleports": 0, "created_on": "2017-12-21T18:32:44Z", "points": 8795}, {"id": 7157188, "course_id": 22100, "map_id": 221, "map_name": "bkz_underground_crypt_v3", "map_stage": 0, "stage_tier": 5, "steam_id": "STEAM_1:0:92323950", "player_name": "Dayan", "mode": "kz_timer", "time": 1384.531, "teleports": 0, "created_on": "2020-07-17T08:40:49Z", "points": 8794}, {"id": 2709982, "course_id": 22100, "map_id": 221, "map_name": "bkz_underground_crypt_v3", "map_stage": 0, "stage_tier": 5, "steam_id": "STEAM_1:0:36849653", "player_name": "Packert", "mode": "kz_timer", "time": 1393.633, "teleports": 0, "created_on": "2019-05-02T08:37:38Z", "points": 8783}, {"id": 13778775, "course_id": 22100, "map_id": 221, "map_name": "bkz_underground_crypt_v3", "map_stage": 0, "stage_tier": 5, "steam_id": "STEAM_1:1:105084996", "player_name": "Miekhi", "mode": "kz_timer", "time": 1399.346, "teleports": 0, "created_on": "2021-09-21T19:35:30Z", "points": 8775}, {"id": 5648037, "course_id": 22100, "map_id": 221, "map_name": "bkz_underground_crypt_v3", "map_stage": 0, "stage_tier": 5, "steam_id": "STEAM_1:1:427508505", "player_name": "belmont3", "mode": "kz_timer", "time": 1400.145, "teleports": 0, "created_on": "2020-04-06T21:26:12Z", "points": 8774}, {"id": 15101258, "course_id": 22100, "map_id": 221, "map_name": "bkz_underground_crypt_v3", "map_stage": 0, "stage_tier": 5, "steam_id": "STEAM_1:1:91481079", "player_name": "(;><)/", "mode": "kz_timer", "time": 1402.146, "teleports": 0, "created_on": "2022-01-26T15:39:00Z", "points": 8770}, {"id": 4225755, "course_id": 22100, "map_id": 221, "map_name": "bkz_underground_crypt_v3", "map_stage": 0, "stage_tier": 5, "steam_id": "STEAM_1:1:34351544", "player_name": "wendong", "mode": "kz_timer", "time": 1403.168, "teleports": 0, "created_on": "2019-11-25T11:37:31Z", "points": 8769}, {"id": 616857, "course_id": 22100, "map_id": 221, "map_name": "bkz_underground_crypt_v3", "map_stage": 0, "stage_tier": 5, "steam_id": "STEAM_1:0:42048280", "player_name": "Ballistic Bacon", "mode": "kz_timer", "time": 1431.203, "teleports": 0, "created_on": "2018-06-05T09:12:56Z", "points": 8729}, {"id": 2256523, "course_id": 22100, "map_id": 221, "map_name": "bkz_underground_crypt_v3", "map_stage": 0, "stage_tier": 5, "steam_id": "STEAM_1:0:62721903", "player_name": "Saw207", "mode": "kz_timer", "time": 1458.953, "teleports": 0, "created_on": "2019-03-12T21:52:12Z", "points": 8689}, {"id": 22455185, "course_id": 22100, "map_id": 221, "map_name": "bkz_underground_crypt_v3", "map_stage": 0, "stage_tier": 5, "steam_id": "STEAM_1:0:99325120", "player_name": "Samm35", "mode": "kz_timer", "time": 1462.494, "teleports": 0, "created_on": "2023-07-31T19:58:59Z", "points": 8682}, {"id": 7009969, "course_id": 22100, "map_id": 221, "map_name": "bkz_underground_crypt_v3", "map_stage": 0, "stage_tier": 5, "steam_id": "STEAM_1:1:10185687", "player_name": "Noah's Ark, I carry all animals", "mode": "kz_timer", "time": 1465.34, "teleports": 0, "created_on": "2020-07-08T00:40:20Z", "points": 8679}, {"id": 19420314, "course_id": 22100, "map_id": 221, "map_name": "bkz_underground_crypt_v3", "map_stage": 0, "stage_tier": 5, "steam_id": "STEAM_1:1:526648385", "player_name": "Fry", "mode": "kz_timer", "time": 1467.188, "teleports": 0, "created_on": "2022-12-31T20:20:20Z", "points": 8676}, {"id": 16614427, "course_id": 22100, "map_id": 221, "map_name": "bkz_underground_crypt_v3", "map_stage": 0, "stage_tier": 5, "steam_id": "STEAM_1:1:114483148", "player_name": "R e e t i r e d.", "mode": "kz_timer", "time": 1474.992, "teleports": 0, "created_on": "2022-05-27T09:34:59Z", "points": 8664}, {"id": 20485242, "course_id": 22100, "map_id": 221, "map_name": "bkz_underground_crypt_v3", "map_stage": 0, "stage_tier": 5, "steam_id": "STEAM_1:0:51074678", "player_name": "ohayo \u1566( \u0361\u00b0 \u035c\u0296 \u0361\u00b0)\u1564", "mode": "kz_timer", "time": 1475.953, "teleports": 0, "created_on": "2023-03-31T18:04:37Z", "points": 8663}, {"id": 4589035, "course_id": 22100, "map_id": 221, "map_name": "bkz_underground_crypt_v3", "map_stage": 0, "stage_tier": 5, "steam_id": "STEAM_1:1:101035890", "player_name": "Bonari", "mode": "kz_timer", "time": 1491.178, "teleports": 0, "created_on": "2020-01-08T14:10:05Z", "points": 8640}, {"id": 10189043, "course_id": 22100, "map_id": 221, "map_name": "bkz_underground_crypt_v3", "map_stage": 0, "stage_tier": 5, "steam_id": "STEAM_1:0:61399935", "player_name": "_max", "mode": "kz_timer", "time": 1496.844, "teleports": 0, "created_on": "2021-01-24T20:42:06Z", "points": 8633}, {"id": 19417991, "course_id": 22100, "map_id": 221, "map_name": "bkz_underground_crypt_v3", "map_stage": 0, "stage_tier": 5, "steam_id": "STEAM_1:1:89886117", "player_name": "rapu chan", "mode": "kz_timer", "time": 1501.641, "teleports": 0, "created_on": "2022-12-31T16:08:37Z", "points": 8626}, {"id": 13316110, "course_id": 22100, "map_id": 221, "map_name": "bkz_underground_crypt_v3", "map_stage": 0, "stage_tier": 5, "steam_id": "STEAM_1:0:46512478", "player_name": "Dostoyevsky", "mode": "kz_timer", "time": 1503.781, "teleports": 0, "created_on": "2021-08-13T16:21:39Z", "points": 8623}, {"id": 16837556, "course_id": 22100, "map_id": 221, "map_name": "bkz_underground_crypt_v3", "map_stage": 0, "stage_tier": 5, "steam_id": "STEAM_1:1:43493432", "player_name": "itzme", "mode": "kz_timer", "time": 1506.039, "teleports": 0, "created_on": "2022-06-14T00:07:38Z", "points": 8621}, {"id": 53291, "course_id": 22100, "map_id": 221, "map_name": "bkz_underground_crypt_v3", "map_stage": 0, "stage_tier": 5, "steam_id": "STEAM_1:0:19212210", "player_name": "Carrier", "mode": "kz_timer", "time": 1514.138, "teleports": 0, "created_on": "2018-02-16T20:16:12Z", "points": 8608}, {"id": 15089420, "course_id": 22100, "map_id": 221, "map_name": "bkz_underground_crypt_v3", "map_stage": 0, "stage_tier": 5, "steam_id": "STEAM_1:0:163375235", "player_name": "mr.Krabs", "mode": "kz_timer", "time": 1515.578, "teleports": 0, "created_on": "2022-01-25T16:21:38Z", "points": 8606}, {"id": 3601, "course_id": 22100, "map_id": 221, "map_name": "bkz_underground_crypt_v3", "map_stage": 0, "stage_tier": 5, "steam_id": "STEAM_1:1:103171896", "player_name": "bw^", "mode": "kz_timer", "time": 1516.44, "teleports": 0, "created_on": "2017-09-25T03:42:35Z", "points": 8605}, {"id": 5071657, "course_id": 22100, "map_id": 221, "map_name": "bkz_underground_crypt_v3", "map_stage": 0, "stage_tier": 5, "steam_id": "STEAM_1:0:60100870", "player_name": "swy\ud800\udc83", "mode": "kz_timer", "time": 1530.609, "teleports": 0, "created_on": "2020-02-24T02:23:36Z", "points": 8584}, {"id": 7158550, "course_id": 22100, "map_id": 221, "map_name": "bkz_underground_crypt_v3", "map_stage": 0, "stage_tier": 5, "steam_id": "STEAM_1:0:69653306", "player_name": "\u4e01\u771f", "mode": "kz_timer", "time": 1533.828, "teleports": 0, "created_on": "2020-07-17T11:04:58Z", "points": 8580}, {"id": 3637831, "course_id": 22100, "map_id": 221, "map_name": "bkz_underground_crypt_v3", "map_stage": 0, "stage_tier": 5, "steam_id": "STEAM_1:0:124040734", "player_name": "S1mp2on", "mode": "kz_timer", "time": 1550.672, "teleports": 0, "created_on": "2019-09-04T04:57:49Z", "points": 8555}, {"id": 19397828, "course_id": 22100, "map_id": 221, "map_name": "bkz_underground_crypt_v3", "map_stage": 0, "stage_tier": 5, "steam_id": "STEAM_1:1:210646321", "player_name": "Garysniffs", "mode": "kz_timer", "time": 1557.617, "teleports": 0, "created_on": "2022-12-30T06:43:23Z", "points": 8545}, {"id": 4590755, "course_id": 22100, "map_id": 221, "map_name": "bkz_underground_crypt_v3", "map_stage": 0, "stage_tier": 5, "steam_id": "STEAM_1:1:38228490", "player_name": "Dudesville", "mode": "kz_timer", "time": 1561.938, "teleports": 0, "created_on": "2020-01-08T17:56:36Z", "points": 8539}, {"id": 5276314, "course_id": 22100, "map_id": 221, "map_name": "bkz_underground_crypt_v3", "map_stage": 0, "stage_tier": 5, "steam_id": "STEAM_1:0:67979286", "player_name": ":3", "mode": "kz_timer", "time": 1562.473, "teleports": 0, "created_on": "2020-03-11T20:04:30Z", "points": 8537}, {"id": 5148119, "course_id": 22100, "map_id": 221, "map_name": "bkz_underground_crypt_v3", "map_stage": 0, "stage_tier": 5, "steam_id": "STEAM_1:1:74590004", "player_name": "Seitoja", "mode": "kz_timer", "time": 1568.305, "teleports": 0, "created_on": "2020-03-01T13:20:30Z", "points": 8528}, {"id": 3575, "course_id": 22100, "map_id": 221, "map_name": "bkz_underground_crypt_v3", "map_stage": 0, "stage_tier": 5, "steam_id": "STEAM_1:0:97795306", "player_name": "Windows 7 \u00ae", "mode": "kz_timer", "time": 1569.18, "teleports": 0, "created_on": "2016-08-05T09:40:04Z", "points": 8527}, {"id": 1104, "course_id": 22100, "map_id": 221, "map_name": "bkz_underground_crypt_v3", "map_stage": 0, "stage_tier": 5, "steam_id": "STEAM_1:0:19858331", "player_name": "JWL", "mode": "kz_timer", "time": 1573.7, "teleports": 0, "created_on": "2016-03-03T20:42:40Z", "points": 8520}, {"id": 6490485, "course_id": 22100, "map_id": 221, "map_name": "bkz_underground_crypt_v3", "map_stage": 0, "stage_tier": 5, "steam_id": "STEAM_1:0:103758169", "player_name": "lew", "mode": "kz_timer", "time": 1576.857, "teleports": 0, "created_on": "2020-05-30T17:25:44Z", "points": 8515}, {"id": 3271400, "course_id": 22100, "map_id": 221, "map_name": "bkz_underground_crypt_v3", "map_stage": 0, "stage_tier": 5, "steam_id": "STEAM_1:1:91436052", "player_name": "STME", "mode": "kz_timer", "time": 1577.969, "teleports": 0, "created_on": "2019-07-12T10:57:58Z", "points": 8514}, {"id": 9625953, "course_id": 22100, "map_id": 221, "map_name": "bkz_underground_crypt_v3", "map_stage": 0, "stage_tier": 5, "steam_id": "STEAM_1:0:66928809", "player_name": "\u00de\u00c0\u2020\u00cek\u00a9", "mode": "kz_timer", "time": 1581.766, "teleports": 0, "created_on": "2020-12-23T19:04:27Z", "points": 8508}, {"id": 7830317, "course_id": 22100, "map_id": 221, "map_name": "bkz_underground_crypt_v3", "map_stage": 0, "stage_tier": 5, "steam_id": "STEAM_1:1:16411902", "player_name": "VertikO", "mode": "kz_timer", "time": 1585.293, "teleports": 0, "created_on": "2020-08-27T21:31:12Z", "points": 8502}, {"id": 10401960, "course_id": 22100, "map_id": 221, "map_name": "bkz_underground_crypt_v3", "map_stage": 0, "stage_tier": 5, "steam_id": "STEAM_1:1:119667737", "player_name": "Avt = D", "mode": "kz_timer", "time": 1585.969, "teleports": 0, "created_on": "2021-02-05T13:09:46Z", "points": 8501}, {"id": 9137368, "course_id": 22100, "map_id": 221, "map_name": "bkz_underground_crypt_v3", "map_stage": 0, "stage_tier": 5, "steam_id": "STEAM_1:1:196398498", "player_name": "Hessu", "mode": "kz_timer", "time": 1595.852, "teleports": 0, "created_on": "2020-11-22T22:47:24Z", "points": 8486}, {"id": 4476, "course_id": 22100, "map_id": 221, "map_name": "bkz_underground_crypt_v3", "map_stage": 0, "stage_tier": 5, "steam_id": "STEAM_1:1:153792789", "player_name": "theax", "mode": "kz_timer", "time": 1609.54, "teleports": 0, "created_on": "2017-12-18T20:41:53Z", "points": 8465}, {"id": 1307807, "course_id": 22100, "map_id": 221, "map_name": "bkz_underground_crypt_v3", "map_stage": 0, "stage_tier": 5, "steam_id": "STEAM_1:0:85747959", "player_name": "san", "mode": "kz_timer", "time": 1610.469, "teleports": 0, "created_on": "2018-10-17T22:42:03Z", "points": 8463}, {"id": 6303682, "course_id": 22100, "map_id": 221, "map_name": "bkz_underground_crypt_v3", "map_stage": 0, "stage_tier": 5, "steam_id": "STEAM_1:0:113151101", "player_name": "Kr0laS", "mode": "kz_timer", "time": 1612.893, "teleports": 0, "created_on": "2020-05-17T20:06:57Z", "points": 8460}, {"id": 6929129, "course_id": 22100, "map_id": 221, "map_name": "bkz_underground_crypt_v3", "map_stage": 0, "stage_tier": 5, "steam_id": "STEAM_1:0:62968659", "player_name": "PaNlk", "mode": "kz_timer", "time": 1621.023, "teleports": 0, "created_on": "2020-07-02T10:52:04Z", "points": 8450}, {"id": 4686051, "course_id": 22100, "map_id": 221, "map_name": "bkz_underground_crypt_v3", "map_stage": 0, "stage_tier": 5, "steam_id": "STEAM_1:0:147128451", "player_name": "let him cook", "mode": "kz_timer", "time": 1626.398, "teleports": 0, "created_on": "2020-01-19T06:02:48Z", "points": 8441}, {"id": 12857638, "course_id": 22100, "map_id": 221, "map_name": "bkz_underground_crypt_v3", "map_stage": 0, "stage_tier": 5, "steam_id": "STEAM_1:1:241442284", "player_name": "\u738b\u6728\u6728", "mode": "kz_timer", "time": 1658.594, "teleports": 0, "created_on": "2021-07-06T10:56:54Z", "points": 8392}, {"id": 19712543, "course_id": 22100, "map_id": 221, "map_name": "bkz_underground_crypt_v3", "map_stage": 0, "stage_tier": 5, "steam_id": "STEAM_1:0:36598024", "player_name": "gwooky", "mode": "kz_timer", "time": 1660.484, "teleports": 0, "created_on": "2023-01-26T10:30:23Z", "points": 8390}, {"id": 4177089, "course_id": 22100, "map_id": 221, "map_name": "bkz_underground_crypt_v3", "map_stage": 0, "stage_tier": 5, "steam_id": "STEAM_1:0:28793437", "player_name": "\u273fFl\u00f8te", "mode": "kz_timer", "time": 1672.992, "teleports": 0, "created_on": "2019-11-17T20:27:16Z", "points": 8373}, {"id": 2643618, "course_id": 22100, "map_id": 221, "map_name": "bkz_underground_crypt_v3", "map_stage": 0, "stage_tier": 5, "steam_id": "STEAM_1:0:148308734", "player_name": "Spk", "mode": "kz_timer", "time": 1683.965, "teleports": 0, "created_on": "2019-04-24T18:15:48Z", "points": 8356}, {"id": 18695580, "course_id": 22100, "map_id": 221, "map_name": "bkz_underground_crypt_v3", "map_stage": 0, "stage_tier": 5, "steam_id": "STEAM_1:1:18698834", "player_name": "Gimli", "mode": "kz_timer", "time": 1690.891, "teleports": 0, "created_on": "2022-10-29T16:53:44Z", "points": 8346}, {"id": 4421890, "course_id": 22100, "map_id": 221, "map_name": "bkz_underground_crypt_v3", "map_stage": 0, "stage_tier": 5, "steam_id": "STEAM_1:0:58420135", "player_name": "Hortt", "mode": "kz_timer", "time": 1699.859, "teleports": 0, "created_on": "2019-12-20T08:42:04Z", "points": 8331}, {"id": 12085798, "course_id": 22100, "map_id": 221, "map_name": "bkz_underground_crypt_v3", "map_stage": 0, "stage_tier": 5, "steam_id": "STEAM_1:0:18220375", "player_name": "funkerman", "mode": "kz_timer", "time": 1702.797, "teleports": 0, "created_on": "2021-05-08T02:54:37Z", "points": 8327}, {"id": 9822323, "course_id": 22100, "map_id": 221, "map_name": "bkz_underground_crypt_v3", "map_stage": 0, "stage_tier": 5, "steam_id": "STEAM_1:1:79287752", "player_name": "Lami", "mode": "kz_timer", "time": 1709.523, "teleports": 0, "created_on": "2021-01-04T16:26:43Z", "points": 8317}, {"id": 13152408, "course_id": 22100, "map_id": 221, "map_name": "bkz_underground_crypt_v3", "map_stage": 0, "stage_tier": 5, "steam_id": "STEAM_1:0:454170511", "player_name": "SxLc:v", "mode": "kz_timer", "time": 1722.805, "teleports": 0, "created_on": "2021-08-01T08:28:58Z", "points": 8299}, {"id": 8128773, "course_id": 22100, "map_id": 221, "map_name": "bkz_underground_crypt_v3", "map_stage": 0, "stage_tier": 5, "steam_id": "STEAM_1:1:79965882", "player_name": "bucket", "mode": "kz_timer", "time": 1753.281, "teleports": 0, "created_on": "2020-09-13T19:15:18Z", "points": 8254}, {"id": 3999431, "course_id": 22100, "map_id": 221, "map_name": "bkz_underground_crypt_v3", "map_stage": 0, "stage_tier": 5, "steam_id": "STEAM_1:0:10663671", "player_name": "\ud5c8\uc811", "mode": "kz_timer", "time": 1795.703, "teleports": 0, "created_on": "2019-10-27T07:52:36Z", "points": 8186}, {"id": 2607934, "course_id": 22100, "map_id": 221, "map_name": "bkz_underground_crypt_v3", "map_stage": 0, "stage_tier": 5, "steam_id": "STEAM_1:0:66828023", "player_name": "mjb", "mode": "kz_timer", "time": 1803.41, "teleports": 0, "created_on": "2019-04-20T22:27:23Z", "points": 8174}, {"id": 7010016, "course_id": 22100, "map_id": 221, "map_name": "bkz_underground_crypt_v3", "map_stage": 0, "stage_tier": 5, "steam_id": "STEAM_1:1:75044279", "player_name": "apploesauce", "mode": "kz_timer", "time": 1810.453, "teleports": 0, "created_on": "2020-07-08T00:47:13Z", "points": 8161}, {"id": 2669654, "course_id": 22100, "map_id": 221, "map_name": "bkz_underground_crypt_v3", "map_stage": 0, "stage_tier": 5, "steam_id": "STEAM_1:0:11714563", "player_name": "raese", "mode": "kz_timer", "time": 1814.797, "teleports": 0, "created_on": "2019-04-27T16:21:35Z", "points": 8153}, {"id": 21123077, "course_id": 22100, "map_id": 221, "map_name": "bkz_underground_crypt_v3", "map_stage": 0, "stage_tier": 5, "steam_id": "STEAM_1:0:206358059", "player_name": "bux", "mode": "kz_timer", "time": 1823.25, "teleports": 0, "created_on": "2023-05-05T13:11:58Z", "points": 8139}, {"id": 20642367, "course_id": 22100, "map_id": 221, "map_name": "bkz_underground_crypt_v3", "map_stage": 0, "stage_tier": 5, "steam_id": "STEAM_1:1:195986308", "player_name": ":^)", "mode": "kz_timer", "time": 1843.125, "teleports": 0, "created_on": "2023-04-08T16:07:49Z", "points": 8107}, {"id": 8849908, "course_id": 22100, "map_id": 221, "map_name": "bkz_underground_crypt_v3", "map_stage": 0, "stage_tier": 5, "steam_id": "STEAM_1:0:99996809", "player_name": "downeel", "mode": "kz_timer", "time": 1855.168, "teleports": 0, "created_on": "2020-11-02T19:41:56Z", "points": 8090}, {"id": 16014810, "course_id": 22100, "map_id": 221, "map_name": "bkz_underground_crypt_v3", "map_stage": 0, "stage_tier": 5, "steam_id": "STEAM_1:1:22075962", "player_name": "inyourdre4mz", "mode": "kz_timer", "time": 1871.021, "teleports": 0, "created_on": "2022-04-10T12:58:23Z", "points": 8065}, {"id": 13864561, "course_id": 22100, "map_id": 221, "map_name": "bkz_underground_crypt_v3", "map_stage": 0, "stage_tier": 5, "steam_id": "STEAM_1:1:129846593", "player_name": "etyg189", "mode": "kz_timer", "time": 1871.086, "teleports": 0, "created_on": "2021-09-30T15:42:34Z", "points": 8064}, {"id": 126164, "course_id": 22100, "map_id": 221, "map_name": "bkz_underground_crypt_v3", "map_stage": 0, "stage_tier": 5, "steam_id": "STEAM_1:0:76312537", "player_name": "Juby", "mode": "kz_timer", "time": 1880.297, "teleports": 0, "created_on": "2018-03-06T14:35:52Z", "points": 8051}, {"id": 20338471, "course_id": 22100, "map_id": 221, "map_name": "bkz_underground_crypt_v3", "map_stage": 0, "stage_tier": 5, "steam_id": "STEAM_1:1:68043173", "player_name": "punc.", "mode": "kz_timer", "time": 1898.648, "teleports": 0, "created_on": "2023-03-23T18:58:36Z", "points": 8024}, {"id": 16195758, "course_id": 22100, "map_id": 221, "map_name": "bkz_underground_crypt_v3", "map_stage": 0, "stage_tier": 5, "steam_id": "STEAM_1:0:58804895", "player_name": "\u6c42\u6c42\u4f60\u522b\u82df\u8fa3", "mode": "kz_timer", "time": 1917.438, "teleports": 0, "created_on": "2022-04-24T13:02:21Z", "points": 7998}, {"id": 19380132, "course_id": 22100, "map_id": 221, "map_name": "bkz_underground_crypt_v3", "map_stage": 0, "stage_tier": 5, "steam_id": "STEAM_1:1:23798951", "player_name": "Jnas Cage", "mode": "kz_timer", "time": 1918.293, "teleports": 0, "created_on": "2022-12-28T22:36:54Z", "points": 7996}, {"id": 7009964, "course_id": 22100, "map_id": 221, "map_name": "bkz_underground_crypt_v3", "map_stage": 0, "stage_tier": 5, "steam_id": "STEAM_1:1:53711411", "player_name": "GiantStorm", "mode": "kz_timer", "time": 1919.406, "teleports": 0, "created_on": "2020-07-08T00:39:14Z", "points": 7994}, {"id": 11422244, "course_id": 22100, "map_id": 221, "map_name": "bkz_underground_crypt_v3", "map_stage": 0, "stage_tier": 5, "steam_id": "STEAM_1:1:116739970", "player_name": "M u g e n", "mode": "kz_timer", "time": 1932.734, "teleports": 0, "created_on": "2021-03-31T17:47:26Z", "points": 7973}, {"id": 4000584, "course_id": 22100, "map_id": 221, "map_name": "bkz_underground_crypt_v3", "map_stage": 0, "stage_tier": 5, "steam_id": "STEAM_1:1:15644863", "player_name": "Chichin", "mode": "kz_timer", "time": 1935.883, "teleports": 0, "created_on": "2019-10-27T11:01:04Z", "points": 7968}, {"id": 2832609, "course_id": 22100, "map_id": 221, "map_name": "bkz_underground_crypt_v3", "map_stage": 0, "stage_tier": 5, "steam_id": "STEAM_1:1:38000222", "player_name": "DZ", "mode": "kz_timer", "time": 1947.953, "teleports": 0, "created_on": "2019-05-17T01:21:49Z", "points": 7949}, {"id": 15496647, "course_id": 22100, "map_id": 221, "map_name": "bkz_underground_crypt_v3", "map_stage": 0, "stage_tier": 5, "steam_id": "STEAM_1:1:74749308", "player_name": "magik", "mode": "kz_timer", "time": 1953.742, "teleports": 0, "created_on": "2022-02-27T04:44:46Z", "points": 7940}, {"id": 4356780, "course_id": 22100, "map_id": 221, "map_name": "bkz_underground_crypt_v3", "map_stage": 0, "stage_tier": 5, "steam_id": "STEAM_1:1:68799954", "player_name": "LEO", "mode": "kz_timer", "time": 1970.969, "teleports": 0, "created_on": "2019-12-11T19:52:39Z", "points": 7913}, {"id": 17567211, "course_id": 22100, "map_id": 221, "map_name": "bkz_underground_crypt_v3", "map_stage": 0, "stage_tier": 5, "steam_id": "STEAM_1:0:422663348", "player_name": "drama", "mode": "kz_timer", "time": 2001.688, "teleports": 0, "created_on": "2022-08-08T15:46:03Z", "points": 7867}, {"id": 11138187, "course_id": 22100, "map_id": 221, "map_name": "bkz_underground_crypt_v3", "map_stage": 0, "stage_tier": 5, "steam_id": "STEAM_1:0:244982795", "player_name": "\u865a\u5984\u306e\u8f6e\u56de", "mode": "kz_timer", "time": 2003.258, "teleports": 0, "created_on": "2021-03-16T14:12:13Z", "points": 7864}, {"id": 9046937, "course_id": 22100, "map_id": 221, "map_name": "bkz_underground_crypt_v3", "map_stage": 0, "stage_tier": 5, "steam_id": "STEAM_1:1:20320506", "player_name": "Matroskin\u30c4", "mode": "kz_timer", "time": 2003.727, "teleports": 0, "created_on": "2020-11-16T19:13:36Z", "points": 7863}, {"id": 14193318, "course_id": 22100, "map_id": 221, "map_name": "bkz_underground_crypt_v3", "map_stage": 0, "stage_tier": 5, "steam_id": "STEAM_1:1:170466007", "player_name": "Kondixell", "mode": "kz_timer", "time": 2021.539, "teleports": 0, "created_on": "2021-11-02T15:16:48Z", "points": 7838}, {"id": 7167943, "course_id": 22100, "map_id": 221, "map_name": "bkz_underground_crypt_v3", "map_stage": 0, "stage_tier": 5, "steam_id": "STEAM_1:1:80301552", "player_name": "dillon", "mode": "kz_timer", "time": 2025.555, "teleports": 0, "created_on": "2020-07-18T01:01:32Z", "points": 7831}, {"id": 7712101, "course_id": 22100, "map_id": 221, "map_name": "bkz_underground_crypt_v3", "map_stage": 0, "stage_tier": 5, "steam_id": "STEAM_1:1:189282780", "player_name": "KipOd", "mode": "kz_timer", "time": 2029.094, "teleports": 0, "created_on": "2020-08-20T20:50:12Z", "points": 7826}, {"id": 2223419, "course_id": 22100, "map_id": 221, "map_name": "bkz_underground_crypt_v3", "map_stage": 0, "stage_tier": 5, "steam_id": "STEAM_1:1:33473118", "player_name": "mrozzz>", "mode": "kz_timer", "time": 2061.25, "teleports": 0, "created_on": "2019-03-07T14:31:11Z", "points": 7782}, {"id": 6686128, "course_id": 22100, "map_id": 221, "map_name": "bkz_underground_crypt_v3", "map_stage": 0, "stage_tier": 5, "steam_id": "STEAM_1:1:42459697", "player_name": "amcat", "mode": "kz_timer", "time": 2070.738, "teleports": 0, "created_on": "2020-06-14T14:32:06Z", "points": 7767}, {"id": 12171056, "course_id": 22100, "map_id": 221, "map_name": "bkz_underground_crypt_v3", "map_stage": 0, "stage_tier": 5, "steam_id": "STEAM_1:0:19273898", "player_name": "bob", "mode": "kz_timer", "time": 2075.82, "teleports": 0, "created_on": "2021-05-13T09:21:14Z", "points": 7758}, {"id": 11175190, "course_id": 22100, "map_id": 221, "map_name": "bkz_underground_crypt_v3", "map_stage": 0, "stage_tier": 5, "steam_id": "STEAM_1:0:545674567", "player_name": "bad vibes forever", "mode": "kz_timer", "time": 2091.043, "teleports": 0, "created_on": "2021-03-18T14:46:19Z", "points": 7738}, {"id": 2657117, "course_id": 22100, "map_id": 221, "map_name": "bkz_underground_crypt_v3", "map_stage": 0, "stage_tier": 5, "steam_id": "STEAM_1:1:20073918", "player_name": "lokki", "mode": "kz_timer", "time": 2092.844, "teleports": 0, "created_on": "2019-04-26T10:26:44Z", "points": 7734}, {"id": 7498683, "course_id": 22100, "map_id": 221, "map_name": "bkz_underground_crypt_v3", "map_stage": 0, "stage_tier": 5, "steam_id": "STEAM_1:0:30824478", "player_name": "lane", "mode": "kz_timer", "time": 2114.895, "teleports": 0, "created_on": "2020-08-08T00:43:26Z", "points": 7702}, {"id": 6416929, "course_id": 22100, "map_id": 221, "map_name": "bkz_underground_crypt_v3", "map_stage": 0, "stage_tier": 5, "steam_id": "STEAM_1:0:1320986", "player_name": "ds\u0279d", "mode": "kz_timer", "time": 2139.664, "teleports": 0, "created_on": "2020-05-25T08:04:41Z", "points": 7669}, {"id": 6668145, "course_id": 22100, "map_id": 221, "map_name": "bkz_underground_crypt_v3", "map_stage": 0, "stage_tier": 5, "steam_id": "STEAM_1:1:95351239", "player_name": "\u20a9PT\u20a9OT\u20a9OMS", "mode": "kz_timer", "time": 2145.133, "teleports": 0, "created_on": "2020-06-13T05:21:26Z", "points": 7662}, {"id": 13040659, "course_id": 22100, "map_id": 221, "map_name": "bkz_underground_crypt_v3", "map_stage": 0, "stage_tier": 5, "steam_id": "STEAM_1:0:142883827", "player_name": "Z", "mode": "kz_timer", "time": 2147.102, "teleports": 0, "created_on": "2021-07-23T05:42:43Z", "points": 7659}, {"id": 1979215, "course_id": 22100, "map_id": 221, "map_name": "bkz_underground_crypt_v3", "map_stage": 0, "stage_tier": 5, "steam_id": "STEAM_1:0:39815535", "player_name": "bertz", "mode": "kz_timer", "time": 2147.527, "teleports": 0, "created_on": "2019-02-02T05:41:12Z", "points": 7657}, {"id": 8882735, "course_id": 22100, "map_id": 221, "map_name": "bkz_underground_crypt_v3", "map_stage": 0, "stage_tier": 5, "steam_id": "STEAM_1:0:73768036", "player_name": "KIWIJORD", "mode": "kz_timer", "time": 2151.969, "teleports": 0, "created_on": "2020-11-05T01:26:43Z", "points": 7650}, {"id": 3305555, "course_id": 22100, "map_id": 221, "map_name": "bkz_underground_crypt_v3", "map_stage": 0, "stage_tier": 5, "steam_id": "STEAM_1:1:244540553", "player_name": "Baby again..", "mode": "kz_timer", "time": 2183.844, "teleports": 0, "created_on": "2019-07-17T11:19:51Z", "points": 7608}, {"id": 1425809, "course_id": 22100, "map_id": 221, "map_name": "bkz_underground_crypt_v3", "map_stage": 0, "stage_tier": 5, "steam_id": "STEAM_1:1:26552715", "player_name": "GabbaGandalf", "mode": "kz_timer", "time": 2184.438, "teleports": 0, "created_on": "2018-11-07T20:16:47Z", "points": 7607}, {"id": 16747485, "course_id": 22100, "map_id": 221, "map_name": "bkz_underground_crypt_v3", "map_stage": 0, "stage_tier": 5, "steam_id": "STEAM_1:0:31119247", "player_name": "_owO", "mode": "kz_timer", "time": 2195.539, "teleports": 0, "created_on": "2022-06-07T06:42:36Z", "points": 7593}, {"id": 7719748, "course_id": 22100, "map_id": 221, "map_name": "bkz_underground_crypt_v3", "map_stage": 0, "stage_tier": 5, "steam_id": "STEAM_1:0:239669875", "player_name": "cute asian girl", "mode": "kz_timer", "time": 2211.453, "teleports": 0, "created_on": "2020-08-21T08:08:12Z", "points": 7571}, {"id": 3087438, "course_id": 22100, "map_id": 221, "map_name": "bkz_underground_crypt_v3", "map_stage": 0, "stage_tier": 5, "steam_id": "STEAM_1:0:177128545", "player_name": "Der Zahlenteufel", "mode": "kz_timer", "time": 2213.23, "teleports": 0, "created_on": "2019-06-17T12:53:13Z", "points": 7568}, {"id": 4283197, "course_id": 22100, "map_id": 221, "map_name": "bkz_underground_crypt_v3", "map_stage": 0, "stage_tier": 5, "steam_id": "STEAM_1:1:29129528", "player_name": "Purkkilo", "mode": "kz_timer", "time": 2226.969, "teleports": 0, "created_on": "2019-12-02T04:32:17Z", "points": 7552}, {"id": 856978, "course_id": 22100, "map_id": 221, "map_name": "bkz_underground_crypt_v3", "map_stage": 0, "stage_tier": 5, "steam_id": "STEAM_1:1:39061360", "player_name": "Danvari", "mode": "kz_timer", "time": 2238.566, "teleports": 0, "created_on": "2018-07-30T14:01:13Z", "points": 7538}, {"id": 13126698, "course_id": 22100, "map_id": 221, "map_name": "bkz_underground_crypt_v3", "map_stage": 0, "stage_tier": 5, "steam_id": "STEAM_1:1:13368494", "player_name": "3dou", "mode": "kz_timer", "time": 2246.945, "teleports": 0, "created_on": "2021-07-30T06:50:16Z", "points": 7526}, {"id": 14867750, "course_id": 22100, "map_id": 221, "map_name": "bkz_underground_crypt_v3", "map_stage": 0, "stage_tier": 5, "steam_id": "STEAM_1:1:89235055", "player_name": "uni", "mode": "kz_timer", "time": 2259.256, "teleports": 0, "created_on": "2022-01-06T20:03:36Z", "points": 7508}, {"id": 156265, "course_id": 22100, "map_id": 221, "map_name": "bkz_underground_crypt_v3", "map_stage": 0, "stage_tier": 5, "steam_id": "STEAM_1:0:4629093", "player_name": "Master <3 g3sg1", "mode": "kz_timer", "time": 2274.336, "teleports": 0, "created_on": "2018-03-12T22:36:27Z", "points": 7486}, {"id": 5463554, "course_id": 22100, "map_id": 221, "map_name": "bkz_underground_crypt_v3", "map_stage": 0, "stage_tier": 5, "steam_id": "STEAM_1:1:106299740", "player_name": "Punisher", "mode": "kz_timer", "time": 2312.648, "teleports": 0, "created_on": "2020-03-25T13:06:36Z", "points": 7435}, {"id": 8110355, "course_id": 22100, "map_id": 221, "map_name": "bkz_underground_crypt_v3", "map_stage": 0, "stage_tier": 5, "steam_id": "STEAM_1:0:192466149", "player_name": "Pulvere", "mode": "kz_timer", "time": 2319.734, "teleports": 0, "created_on": "2020-09-12T18:40:34Z", "points": 7427}, {"id": 724502, "course_id": 22100, "map_id": 221, "map_name": "bkz_underground_crypt_v3", "map_stage": 0, "stage_tier": 5, "steam_id": "STEAM_1:1:4308378", "player_name": "EXTRA WHITE SAUCE", "mode": "kz_timer", "time": 2370.387, "teleports": 0, "created_on": "2018-06-22T23:33:02Z", "points": 7361}, {"id": 1588766, "course_id": 22100, "map_id": 221, "map_name": "bkz_underground_crypt_v3", "map_stage": 0, "stage_tier": 5, "steam_id": "STEAM_1:0:87950310", "player_name": "broiiler", "mode": "kz_timer", "time": 2396.758, "teleports": 0, "created_on": "2018-12-04T19:12:51Z", "points": 7327}, {"id": 17707892, "course_id": 22100, "map_id": 221, "map_name": "bkz_underground_crypt_v3", "map_stage": 0, "stage_tier": 5, "steam_id": "STEAM_1:1:186113493", "player_name": "\u0421\u0435\u0440\u044b\u0439 \u043a\u043e\u0442\u043e\u0440\u044b\u0439 \u0431\u0435\u043b\u044b\u0439 \u043d\u0435 \u0447\u0435\u0440\u043d\u044b\u0439", "mode": "kz_timer", "time": 2468.664, "teleports": 0, "created_on": "2022-08-17T19:24:28Z", "points": 7241}, {"id": 13788875, "course_id": 22100, "map_id": 221, "map_name": "bkz_underground_crypt_v3", "map_stage": 0, "stage_tier": 5, "steam_id": "STEAM_1:1:30439775", "player_name": "xcobet", "mode": "kz_timer", "time": 2486.045, "teleports": 0, "created_on": "2021-09-23T07:26:38Z", "points": 7219}, {"id": 20721203, "course_id": 22100, "map_id": 221, "map_name": "bkz_underground_crypt_v3", "map_stage": 0, "stage_tier": 5, "steam_id": "STEAM_1:0:44358139", "player_name": "stanie-", "mode": "kz_timer", "time": 2589.676, "teleports": 0, "created_on": "2023-04-12T18:19:49Z", "points": 7096}, {"id": 14776843, "course_id": 22100, "map_id": 221, "map_name": "bkz_underground_crypt_v3", "map_stage": 0, "stage_tier": 5, "steam_id": "STEAM_1:1:168575119", "player_name": "Flonnych", "mode": "kz_timer", "time": 2599.359, "teleports": 0, "created_on": "2021-12-29T13:33:32Z", "points": 7082}, {"id": 5201992, "course_id": 22100, "map_id": 221, "map_name": "bkz_underground_crypt_v3", "map_stage": 0, "stage_tier": 5, "steam_id": "STEAM_1:0:229467652", "player_name": "..", "mode": "kz_timer", "time": 2616.133, "teleports": 0, "created_on": "2020-03-05T17:51:01Z", "points": 7063}, {"id": 17928416, "course_id": 22100, "map_id": 221, "map_name": "bkz_underground_crypt_v3", "map_stage": 0, "stage_tier": 5, "steam_id": "STEAM_1:1:549804061", "player_name": "06334159422", "mode": "kz_timer", "time": 2619.633, "teleports": 0, "created_on": "2022-09-01T17:23:16Z", "points": 7059}, {"id": 1164492, "course_id": 22100, "map_id": 221, "map_name": "bkz_underground_crypt_v3", "map_stage": 0, "stage_tier": 5, "steam_id": "STEAM_1:1:213837979", "player_name": "borb ==[BMF]==", "mode": "kz_timer", "time": 2625.143, "teleports": 0, "created_on": "2018-09-20T16:47:49Z", "points": 7051}, {"id": 7498037, "course_id": 22100, "map_id": 221, "map_name": "bkz_underground_crypt_v3", "map_stage": 0, "stage_tier": 5, "steam_id": "STEAM_1:1:121490593", "player_name": "Capri", "mode": "kz_timer", "time": 2627.219, "teleports": 0, "created_on": "2020-08-07T23:40:55Z", "points": 7049}, {"id": 3489630, "course_id": 22100, "map_id": 221, "map_name": "bkz_underground_crypt_v3", "map_stage": 0, "stage_tier": 5, "steam_id": "STEAM_1:1:9585303", "player_name": "masque", "mode": "kz_timer", "time": 2628.898, "teleports": 0, "created_on": "2019-08-13T05:22:27Z", "points": 7047}, {"id": 7830677, "course_id": 22100, "map_id": 221, "map_name": "bkz_underground_crypt_v3", "map_stage": 0, "stage_tier": 5, "steam_id": "STEAM_1:1:532273515", "player_name": "PaaVo", "mode": "kz_timer", "time": 2634.688, "teleports": 0, "created_on": "2020-08-27T22:03:23Z", "points": 7038}, {"id": 8335926, "course_id": 22100, "map_id": 221, "map_name": "bkz_underground_crypt_v3", "map_stage": 0, "stage_tier": 5, "steam_id": "STEAM_1:0:454476423", "player_name": " \u043c\u9d7a\u03b3'\u0439\u25c6\u216bA", "mode": "kz_timer", "time": 2726.176, "teleports": 0, "created_on": "2020-09-27T12:41:36Z", "points": 6942}, {"id": 13857556, "course_id": 22100, "map_id": 221, "map_name": "bkz_underground_crypt_v3", "map_stage": 0, "stage_tier": 5, "steam_id": "STEAM_1:1:100820400", "player_name": "uber", "mode": "kz_timer", "time": 2795.172, "teleports": 0, "created_on": "2021-09-29T22:00:31Z", "points": 6869}, {"id": 11434576, "course_id": 22100, "map_id": 221, "map_name": "bkz_underground_crypt_v3", "map_stage": 0, "stage_tier": 5, "steam_id": "STEAM_1:1:35438192", "player_name": "fredrik", "mode": "kz_timer", "time": 2797.445, "teleports": 0, "created_on": "2021-04-01T12:00:15Z", "points": 6867}, {"id": 288594, "course_id": 22100, "map_id": 221, "map_name": "bkz_underground_crypt_v3", "map_stage": 0, "stage_tier": 5, "steam_id": "STEAM_1:1:225435469", "player_name": "0V3R7H1NK3R", "mode": "kz_timer", "time": 2839.773, "teleports": 0, "created_on": "2018-04-09T13:50:08Z", "points": 6823}, {"id": 4307994, "course_id": 22100, "map_id": 221, "map_name": "bkz_underground_crypt_v3", "map_stage": 0, "stage_tier": 5, "steam_id": "STEAM_1:0:197242264", "player_name": "covid", "mode": "kz_timer", "time": 2852.68, "teleports": 0, "created_on": "2019-12-05T13:34:04Z", "points": 6811}, {"id": 1327161, "course_id": 22100, "map_id": 221, "map_name": "bkz_underground_crypt_v3", "map_stage": 0, "stage_tier": 5, "steam_id": "STEAM_1:0:64768095", "player_name": "MIKAS222++", "mode": "kz_timer", "time": 2855.266, "teleports": 0, "created_on": "2018-10-21T14:41:57Z", "points": 6808}, {"id": 2670762, "course_id": 22100, "map_id": 221, "map_name": "bkz_underground_crypt_v3", "map_stage": 0, "stage_tier": 5, "steam_id": "STEAM_1:0:143593386", "player_name": "quack", "mode": "kz_timer", "time": 2881.313, "teleports": 0, "created_on": "2019-04-27T18:04:47Z", "points": 6783}, {"id": 3346786, "course_id": 22100, "map_id": 221, "map_name": "bkz_underground_crypt_v3", "map_stage": 0, "stage_tier": 5, "steam_id": "STEAM_1:0:63765498", "player_name": "Maya", "mode": "kz_timer", "time": 2894.023, "teleports": 0, "created_on": "2019-07-23T02:58:35Z", "points": 6770}, {"id": 3381779, "course_id": 22100, "map_id": 221, "map_name": "bkz_underground_crypt_v3", "map_stage": 0, "stage_tier": 5, "steam_id": "STEAM_1:1:15002291", "player_name": "\uff03 \u0410\u043a\u0432 E_No", "mode": "kz_timer", "time": 2903.813, "teleports": 0, "created_on": "2019-07-28T10:12:54Z", "points": 6760}, {"id": 21428292, "course_id": 22100, "map_id": 221, "map_name": "bkz_underground_crypt_v3", "map_stage": 0, "stage_tier": 5, "steam_id": "STEAM_1:1:164726559", "player_name": "Floppy", "mode": "kz_timer", "time": 2936.828, "teleports": 0, "created_on": "2023-05-26T09:09:20Z", "points": 6729}, {"id": 8346166, "course_id": 22100, "map_id": 221, "map_name": "bkz_underground_crypt_v3", "map_stage": 0, "stage_tier": 5, "steam_id": "STEAM_1:0:86429878", "player_name": "BigMitch128", "mode": "kz_timer", "time": 2981.828, "teleports": 0, "created_on": "2020-09-28T04:37:41Z", "points": 6682}, {"id": 7168091, "course_id": 22100, "map_id": 221, "map_name": "bkz_underground_crypt_v3", "map_stage": 0, "stage_tier": 5, "steam_id": "STEAM_1:0:52634975", "player_name": "beef stew", "mode": "kz_timer", "time": 3003.844, "teleports": 0, "created_on": "2020-07-18T01:13:37Z", "points": 6663}, {"id": 12648514, "course_id": 22100, "map_id": 221, "map_name": "bkz_underground_crypt_v3", "map_stage": 0, "stage_tier": 5, "steam_id": "STEAM_1:0:1564639", "player_name": "FrozeEnd", "mode": "kz_timer", "time": 3041.797, "teleports": 0, "created_on": "2021-06-14T07:48:36Z", "points": 6628}, {"id": 13112246, "course_id": 22100, "map_id": 221, "map_name": "bkz_underground_crypt_v3", "map_stage": 0, "stage_tier": 5, "steam_id": "STEAM_1:1:212386217", "player_name": "candei", "mode": "kz_timer", "time": 3049.82, "teleports": 0, "created_on": "2021-07-29T01:56:37Z", "points": 6620}, {"id": 15894028, "course_id": 22100, "map_id": 221, "map_name": "bkz_underground_crypt_v3", "map_stage": 0, "stage_tier": 5, "steam_id": "STEAM_1:1:24049284", "player_name": "Harry_Pootha", "mode": "kz_timer", "time": 3144.242, "teleports": 0, "created_on": "2022-03-30T21:12:50Z", "points": 6529}, {"id": 8301688, "course_id": 22100, "map_id": 221, "map_name": "bkz_underground_crypt_v3", "map_stage": 0, "stage_tier": 5, "steam_id": "STEAM_1:1:128648428", "player_name": "9s", "mode": "kz_timer", "time": 3159.023, "teleports": 0, "created_on": "2020-09-25T05:30:52Z", "points": 6517}, {"id": 2876670, "course_id": 22100, "map_id": 221, "map_name": "bkz_underground_crypt_v3", "map_stage": 0, "stage_tier": 5, "steam_id": "STEAM_1:0:41353755", "player_name": "AlienatedTrash", "mode": "kz_timer", "time": 3167.375, "teleports": 0, "created_on": "2019-05-21T23:46:33Z", "points": 6510}, {"id": 14161249, "course_id": 22100, "map_id": 221, "map_name": "bkz_underground_crypt_v3", "map_stage": 0, "stage_tier": 5, "steam_id": "STEAM_1:1:59339446", "player_name": "\udb40\udc21\udb40\udc21\u2067\u2067AsqueN", "mode": "kz_timer", "time": 3169.162, "teleports": 0, "created_on": "2021-10-30T11:28:04Z", "points": 6507}, {"id": 21759361, "course_id": 22100, "map_id": 221, "map_name": "bkz_underground_crypt_v3", "map_stage": 0, "stage_tier": 5, "steam_id": "STEAM_1:1:5455072", "player_name": "shotgun sally", "mode": "kz_timer", "time": 3207.25, "teleports": 0, "created_on": "2023-06-14T04:45:09Z", "points": 6475}, {"id": 19420472, "course_id": 22100, "map_id": 221, "map_name": "bkz_underground_crypt_v3", "map_stage": 0, "stage_tier": 5, "steam_id": "STEAM_1:0:49561250", "player_name": "Cafufu", "mode": "kz_timer", "time": 3250.703, "teleports": 0, "created_on": "2022-12-31T20:46:11Z", "points": 6435}, {"id": 16014967, "course_id": 22100, "map_id": 221, "map_name": "bkz_underground_crypt_v3", "map_stage": 0, "stage_tier": 5, "steam_id": "STEAM_1:1:195006022", "player_name": "alex", "mode": "kz_timer", "time": 3255.488, "teleports": 0, "created_on": "2022-04-10T13:10:32Z", "points": 6431}, {"id": 3574930, "course_id": 22100, "map_id": 221, "map_name": "bkz_underground_crypt_v3", "map_stage": 0, "stage_tier": 5, "steam_id": "STEAM_1:1:172389327", "player_name": ".pazii", "mode": "kz_timer", "time": 3271.969, "teleports": 0, "created_on": "2019-08-25T15:18:11Z", "points": 6418}, {"id": 1626759, "course_id": 22100, "map_id": 221, "map_name": "bkz_underground_crypt_v3", "map_stage": 0, "stage_tier": 5, "steam_id": "STEAM_1:0:19345271", "player_name": "Mylifetogive", "mode": "kz_timer", "time": 3337.182, "teleports": 0, "created_on": "2018-12-15T21:20:26Z", "points": 6369}, {"id": 11574100, "course_id": 22100, "map_id": 221, "map_name": "bkz_underground_crypt_v3", "map_stage": 0, "stage_tier": 5, "steam_id": "STEAM_1:0:238627919", "player_name": "roxas", "mode": "kz_timer", "time": 3385.953, "teleports": 0, "created_on": "2021-04-08T23:21:05Z", "points": 6330}, {"id": 18397683, "course_id": 22100, "map_id": 221, "map_name": "bkz_underground_crypt_v3", "map_stage": 0, "stage_tier": 5, "steam_id": "STEAM_1:0:64663431", "player_name": "oll9abc", "mode": "kz_timer", "time": 3395.102, "teleports": 0, "created_on": "2022-10-04T05:09:59Z", "points": 6322}, {"id": 7498360, "course_id": 22100, "map_id": 221, "map_name": "bkz_underground_crypt_v3", "map_stage": 0, "stage_tier": 5, "steam_id": "STEAM_1:0:176700598", "player_name": "sus", "mode": "kz_timer", "time": 3543.566, "teleports": 0, "created_on": "2020-08-08T00:09:32Z", "points": 6214}, {"id": 18800264, "course_id": 22100, "map_id": 221, "map_name": "bkz_underground_crypt_v3", "map_stage": 0, "stage_tier": 5, "steam_id": "STEAM_1:0:464583072", "player_name": "hamyak kredo", "mode": "kz_timer", "time": 3708.984, "teleports": 0, "created_on": "2022-11-06T10:38:22Z", "points": 6106}, {"id": 4357085, "course_id": 22100, "map_id": 221, "map_name": "bkz_underground_crypt_v3", "map_stage": 0, "stage_tier": 5, "steam_id": "STEAM_1:1:55230187", "player_name": "Ed", "mode": "kz_timer", "time": 3742.695, "teleports": 0, "created_on": "2019-12-11T20:58:18Z", "points": 6085}, {"id": 3539744, "course_id": 22100, "map_id": 221, "map_name": "bkz_underground_crypt_v3", "map_stage": 0, "stage_tier": 5, "steam_id": "STEAM_1:1:167770482", "player_name": "ramuk_neerus", "mode": "kz_timer", "time": 3847.641, "teleports": 0, "created_on": "2019-08-20T06:40:11Z", "points": 6022}, {"id": 7860807, "course_id": 22100, "map_id": 221, "map_name": "bkz_underground_crypt_v3", "map_stage": 0, "stage_tier": 5, "steam_id": "STEAM_1:0:111775675", "player_name": "bainz", "mode": "kz_timer", "time": 3866.383, "teleports": 0, "created_on": "2020-08-29T14:08:14Z", "points": 6013}, {"id": 15877045, "course_id": 22100, "map_id": 221, "map_name": "bkz_underground_crypt_v3", "map_stage": 0, "stage_tier": 5, "steam_id": "STEAM_1:0:129656982", "player_name": "KaKa47", "mode": "kz_timer", "time": 3897.711, "teleports": 0, "created_on": "2022-03-29T09:37:00Z", "points": 5993}, {"id": 3950010, "course_id": 22100, "map_id": 221, "map_name": "bkz_underground_crypt_v3", "map_stage": 0, "stage_tier": 5, "steam_id": "STEAM_1:1:123487235", "player_name": "dynamic", "mode": "kz_timer", "time": 3929.836, "teleports": 0, "created_on": "2019-10-21T02:00:35Z", "points": 5977}, {"id": 7575639, "course_id": 22100, "map_id": 221, "map_name": "bkz_underground_crypt_v3", "map_stage": 0, "stage_tier": 5, "steam_id": "STEAM_1:0:111970983", "player_name": "Budal", "mode": "kz_timer", "time": 3988.625, "teleports": 0, "created_on": "2020-08-13T00:19:06Z", "points": 5945}, {"id": 2161316, "course_id": 22100, "map_id": 221, "map_name": "bkz_underground_crypt_v3", "map_stage": 0, "stage_tier": 5, "steam_id": "STEAM_1:0:2442409", "player_name": "zeld0", "mode": "kz_timer", "time": 3993.566, "teleports": 0, "created_on": "2019-02-27T04:11:38Z", "points": 5942}, {"id": 4695577, "course_id": 22100, "map_id": 221, "map_name": "bkz_underground_crypt_v3", "map_stage": 0, "stage_tier": 5, "steam_id": "STEAM_1:1:121506781", "player_name": "bidoofd", "mode": "kz_timer", "time": 4073.367, "teleports": 0, "created_on": "2020-01-20T03:40:52Z", "points": 5901}, {"id": 8600059, "course_id": 22100, "map_id": 221, "map_name": "bkz_underground_crypt_v3", "map_stage": 0, "stage_tier": 5, "steam_id": "STEAM_1:0:78418878", "player_name": "Toasty", "mode": "kz_timer", "time": 4118.719, "teleports": 0, "created_on": "2020-10-16T05:56:55Z", "points": 5877}, {"id": 21152843, "course_id": 22100, "map_id": 221, "map_name": "bkz_underground_crypt_v3", "map_stage": 0, "stage_tier": 5, "steam_id": "STEAM_1:0:177050749", "player_name": "yzc", "mode": "kz_timer", "time": 4125.07, "teleports": 0, "created_on": "2023-05-07T08:09:32Z", "points": 5874}, {"id": 1705019, "course_id": 22100, "map_id": 221, "map_name": "bkz_underground_crypt_v3", "map_stage": 0, "stage_tier": 5, "steam_id": "STEAM_1:1:35068110", "player_name": "j", "mode": "kz_timer", "time": 4130.516, "teleports": 0, "created_on": "2018-12-28T18:12:15Z", "points": 5871}, {"id": 11571632, "course_id": 22100, "map_id": 221, "map_name": "bkz_underground_crypt_v3", "map_stage": 0, "stage_tier": 5, "steam_id": "STEAM_1:0:218736011", "player_name": "\u00f6yygh", "mode": "kz_timer", "time": 4202.148, "teleports": 0, "created_on": "2021-04-08T20:29:41Z", "points": 5838}, {"id": 1343304, "course_id": 22100, "map_id": 221, "map_name": "bkz_underground_crypt_v3", "map_stage": 0, "stage_tier": 5, "steam_id": "STEAM_1:1:804915", "player_name": "TomTomasson", "mode": "kz_timer", "time": 4786.328, "teleports": 0, "created_on": "2018-10-24T19:45:47Z", "points": 5596}, {"id": 2831875, "course_id": 22100, "map_id": 221, "map_name": "bkz_underground_crypt_v3", "map_stage": 0, "stage_tier": 5, "steam_id": "STEAM_1:1:67058378", "player_name": "xq", "mode": "kz_timer", "time": 5017.375, "teleports": 0, "created_on": "2019-05-16T22:37:42Z", "points": 5552}, {"id": 11434525, "course_id": 22100, "map_id": 221, "map_name": "bkz_underground_crypt_v3", "map_stage": 0, "stage_tier": 5, "steam_id": "STEAM_1:1:13989108", "player_name": "TELIA.SE", "mode": "kz_timer", "time": 6050.352, "teleports": 0, "created_on": "2021-04-01T11:57:02Z", "points": 5519}]