[{"id": 21154551, "course_id": 83500, "map_id": 835, "map_name": "kz_symmetry", "map_stage": 0, "stage_tier": 2, "steam_id": "STEAM_1:0:170851004", "player_name": "\u857e\u59ae\u00b7\u970d\u666e\u00b7\u5e03\u840a\u897f", "mode": "kz_timer", "time": 37.109, "teleports": 0, "created_on": "2023-05-07T09:59:22Z", "points": 10000}, {"id": 14416850, "course_id": 83500, "map_id": 835, "map_name": "kz_symmetry", "map_stage": 0, "stage_tier": 2, "steam_id": "STEAM_1:1:194388317", "player_name": "matti sami", "mode": "kz_timer", "time": 84.055, "teleports": 0, "created_on": "2021-11-25T12:58:19Z", "points": 9858}, {"id": 12469436, "course_id": 83500, "map_id": 835, "map_name": "kz_symmetry", "map_stage": 0, "stage_tier": 2, "steam_id": "STEAM_1:1:11621314", "player_name": "-}{0}{0JI_SLaYeR-", "mode": "kz_timer", "time": 87.797, "teleports": 0, "created_on": "2021-06-01T20:17:05Z", "points": 9791}, {"id": 13076022, "course_id": 83500, "map_id": 835, "map_name": "kz_symmetry", "map_stage": 0, "stage_tier": 2, "steam_id": "STEAM_1:1:51653737", "player_name": "alves", "mode": "kz_timer", "time": 88.766, "teleports": 0, "created_on": "2021-07-26T01:40:39Z", "points": 9650}, {"id": 12468428, "course_id": 83500, "map_id": 835, "map_name": "kz_symmetry", "map_stage": 0, "stage_tier": 2, "steam_id": "STEAM_1:0:436307804", "player_name": "Zanxy", "mode": "kz_timer", "time": 89.367, "teleports": 0, "created_on": "2021-06-01T18:59:15Z", "points": 9649}, {"id": 11286379, "course_id": 83500, "map_id": 835, "map_name": "kz_symmetry", "map_stage": 0, "stage_tier": 2, "steam_id": "STEAM_1:0:143988804", "player_name": "cocksu", "mode": "kz_timer", "time": 91.531, "teleports": 0, "created_on": "2021-03-24T15:22:09Z", "points": 9595}, {"id": 15882801, "course_id": 83500, "map_id": 835, "map_name": "kz_symmetry", "map_stage": 0, "stage_tier": 2, "steam_id": "STEAM_1:1:116332646", "player_name": "assass1n", "mode": "kz_timer", "time": 92.834, "teleports": 0, "created_on": "2022-03-29T18:21:53Z", "points": 9565}, {"id": 11583053, "course_id": 83500, "map_id": 835, "map_name": "kz_symmetry", "map_stage": 0, "stage_tier": 2, "steam_id": "STEAM_1:0:142574868", "player_name": "TrickZ", "mode": "kz_timer", "time": 94.188, "teleports": 0, "created_on": "2021-04-09T13:29:03Z", "points": 9535}, {"id": 8062703, "course_id": 83500, "map_id": 835, "map_name": "kz_symmetry", "map_stage": 0, "stage_tier": 2, "steam_id": "STEAM_1:1:6716268", "player_name": "\u771f\u591c\u4e2d\u306e\u30c9\u30a2", "mode": "kz_timer", "time": 99.109, "teleports": 0, "created_on": "2020-09-09T21:52:11Z", "points": 9445}, {"id": 18906084, "course_id": 83500, "map_id": 835, "map_name": "kz_symmetry", "map_stage": 0, "stage_tier": 2, "steam_id": "STEAM_1:1:18116709", "player_name": "z1c", "mode": "kz_timer", "time": 102.461, "teleports": 0, "created_on": "2022-11-13T11:56:23Z", "points": 9327}, {"id": 19303346, "course_id": 83500, "map_id": 835, "map_name": "kz_symmetry", "map_stage": 0, "stage_tier": 2, "steam_id": "STEAM_1:0:27080650", "player_name": "pezizz", "mode": "kz_timer", "time": 102.836, "teleports": 0, "created_on": "2022-12-23T07:26:31Z", "points": 9326}, {"id": 8069412, "course_id": 83500, "map_id": 835, "map_name": "kz_symmetry", "map_stage": 0, "stage_tier": 2, "steam_id": "STEAM_1:1:203024318", "player_name": "a", "mode": "kz_timer", "time": 103.438, "teleports": 0, "created_on": "2020-09-10T09:15:55Z", "points": 9297}, {"id": 21320121, "course_id": 83500, "map_id": 835, "map_name": "kz_symmetry", "map_stage": 0, "stage_tier": 2, "steam_id": "STEAM_1:0:219573998", "player_name": "\u4eca\u751f-Lzd", "mode": "kz_timer", "time": 105.617, "teleports": 0, "created_on": "2023-05-19T06:39:26Z", "points": 9266}, {"id": 13125261, "course_id": 83500, "map_id": 835, "map_name": "kz_symmetry", "map_stage": 0, "stage_tier": 2, "steam_id": "STEAM_1:1:497395759", "player_name": "pogo", "mode": "kz_timer", "time": 108.0, "teleports": 0, "created_on": "2021-07-30T03:03:11Z", "points": 9177}, {"id": 8828059, "course_id": 83500, "map_id": 835, "map_name": "kz_symmetry", "map_stage": 0, "stage_tier": 2, "steam_id": "STEAM_1:0:94410862", "player_name": "kuu", "mode": "kz_timer", "time": 108.085, "teleports": 0, "created_on": "2020-11-01T08:31:02Z", "points": 9177}, {"id": 11585207, "course_id": 83500, "map_id": 835, "map_name": "kz_symmetry", "map_stage": 0, "stage_tier": 2, "steam_id": "STEAM_1:0:39248891", "player_name": "Ginger", "mode": "kz_timer", "time": 108.609, "teleports": 0, "created_on": "2021-04-09T15:08:53Z", "points": 9143}, {"id": 20395151, "course_id": 83500, "map_id": 835, "map_name": "kz_symmetry", "map_stage": 0, "stage_tier": 2, "steam_id": "STEAM_1:1:472561192", "player_name": "Ferrum", "mode": "kz_timer", "time": 108.727, "teleports": 0, "created_on": "2023-03-26T19:47:50Z", "points": 9143}, {"id": 8817472, "course_id": 83500, "map_id": 835, "map_name": "kz_symmetry", "map_stage": 0, "stage_tier": 2, "steam_id": "STEAM_1:1:128389518", "player_name": "Exusiai", "mode": "kz_timer", "time": 111.133, "teleports": 0, "created_on": "2020-10-31T15:07:13Z", "points": 9120}, {"id": 8541921, "course_id": 83500, "map_id": 835, "map_name": "kz_symmetry", "map_stage": 0, "stage_tier": 2, "steam_id": "STEAM_1:1:23960079", "player_name": "LEWLY", "mode": "kz_timer", "time": 111.898, "teleports": 0, "created_on": "2020-10-11T19:35:51Z", "points": 9109}, {"id": 8325780, "course_id": 83500, "map_id": 835, "map_name": "kz_symmetry", "map_stage": 0, "stage_tier": 2, "steam_id": "STEAM_1:0:90225250", "player_name": "sage :D", "mode": "kz_timer", "time": 123.547, "teleports": 0, "created_on": "2020-09-26T19:27:18Z", "points": 8974}, {"id": 8040785, "course_id": 83500, "map_id": 835, "map_name": "kz_symmetry", "map_stage": 0, "stage_tier": 2, "steam_id": "STEAM_1:1:51660477", "player_name": "vmi", "mode": "kz_timer", "time": 127.07, "teleports": 0, "created_on": "2020-09-08T16:46:46Z", "points": 8929}, {"id": 8051527, "course_id": 83500, "map_id": 835, "map_name": "kz_symmetry", "map_stage": 0, "stage_tier": 2, "steam_id": "STEAM_1:1:160428314", "player_name": "yuki.", "mode": "kz_timer", "time": 129.945, "teleports": 0, "created_on": "2020-09-09T08:36:09Z", "points": 8894}, {"id": 16327399, "course_id": 83500, "map_id": 835, "map_name": "kz_symmetry", "map_stage": 0, "stage_tier": 2, "steam_id": "STEAM_1:0:178573631", "player_name": "AyayaBoy :D", "mode": "kz_timer", "time": 132.016, "teleports": 0, "created_on": "2022-05-04T15:23:17Z", "points": 8871}, {"id": 13154162, "course_id": 83500, "map_id": 835, "map_name": "kz_symmetry", "map_stage": 0, "stage_tier": 2, "steam_id": "STEAM_1:1:69686392", "player_name": "rasane =))", "mode": "kz_timer", "time": 134.063, "teleports": 0, "created_on": "2021-08-01T11:44:54Z", "points": 8852}, {"id": 8255454, "course_id": 83500, "map_id": 835, "map_name": "kz_symmetry", "map_stage": 0, "stage_tier": 2, "steam_id": "STEAM_1:1:91208527", "player_name": "Fksch", "mode": "kz_timer", "time": 134.656, "teleports": 0, "created_on": "2020-09-22T00:57:36Z", "points": 8837}, {"id": 22154340, "course_id": 83500, "map_id": 835, "map_name": "kz_symmetry", "map_stage": 0, "stage_tier": 2, "steam_id": "STEAM_1:0:73768036", "player_name": "KIWIJORD", "mode": "kz_timer", "time": 136.656, "teleports": 0, "created_on": "2023-07-11T03:40:59Z", "points": 8798}, {"id": 22408986, "course_id": 83500, "map_id": 835, "map_name": "kz_symmetry", "map_stage": 0, "stage_tier": 2, "steam_id": "STEAM_1:0:171477260", "player_name": "SunL", "mode": "kz_timer", "time": 141.117, "teleports": 0, "created_on": "2023-07-28T20:34:16Z", "points": 8710}, {"id": 8285812, "course_id": 83500, "map_id": 835, "map_name": "kz_symmetry", "map_stage": 0, "stage_tier": 2, "steam_id": "STEAM_1:0:183399738", "player_name": "ERiiC", "mode": "kz_timer", "time": 143.547, "teleports": 0, "created_on": "2020-09-24T01:25:51Z", "points": 8695}, {"id": 8151945, "course_id": 83500, "map_id": 835, "map_name": "kz_symmetry", "map_stage": 0, "stage_tier": 2, "steam_id": "STEAM_1:1:196398498", "player_name": "Hessu", "mode": "kz_timer", "time": 145.008, "teleports": 0, "created_on": "2020-09-15T08:40:14Z", "points": 8691}, {"id": 15849262, "course_id": 83500, "map_id": 835, "map_name": "kz_symmetry", "map_stage": 0, "stage_tier": 2, "steam_id": "STEAM_1:1:100888527", "player_name": "Invers", "mode": "kz_timer", "time": 145.102, "teleports": 0, "created_on": "2022-03-26T14:43:27Z", "points": 8690}, {"id": 10304250, "course_id": 83500, "map_id": 835, "map_name": "kz_symmetry", "map_stage": 0, "stage_tier": 2, "steam_id": "STEAM_1:1:215316949", "player_name": "Furri (bullyhunter until june)", "mode": "kz_timer", "time": 146.031, "teleports": 0, "created_on": "2021-01-31T04:35:20Z", "points": 8688}, {"id": 12122845, "course_id": 83500, "map_id": 835, "map_name": "kz_symmetry", "map_stage": 0, "stage_tier": 2, "steam_id": "STEAM_1:1:95129311", "player_name": "Mei Nagant", "mode": "kz_timer", "time": 146.172, "teleports": 0, "created_on": "2021-05-10T08:22:56Z", "points": 8687}, {"id": 8029446, "course_id": 83500, "map_id": 835, "map_name": "kz_symmetry", "map_stage": 0, "stage_tier": 2, "steam_id": "STEAM_1:1:80301552", "player_name": "dillon", "mode": "kz_timer", "time": 146.742, "teleports": 0, "created_on": "2020-09-08T02:34:48Z", "points": 8686}, {"id": 11297838, "course_id": 83500, "map_id": 835, "map_name": "kz_symmetry", "map_stage": 0, "stage_tier": 2, "steam_id": "STEAM_1:0:164106861", "player_name": "mango", "mode": "kz_timer", "time": 146.922, "teleports": 0, "created_on": "2021-03-25T05:02:16Z", "points": 8685}, {"id": 17266832, "course_id": 83500, "map_id": 835, "map_name": "kz_symmetry", "map_stage": 0, "stage_tier": 2, "steam_id": "STEAM_1:1:196861182", "player_name": "puff.", "mode": "kz_timer", "time": 147.953, "teleports": 0, "created_on": "2022-07-18T22:28:47Z", "points": 8682}, {"id": 8140213, "course_id": 83500, "map_id": 835, "map_name": "kz_symmetry", "map_stage": 0, "stage_tier": 2, "steam_id": "STEAM_1:1:192680451", "player_name": "sNs", "mode": "kz_timer", "time": 150.633, "teleports": 0, "created_on": "2020-09-14T14:26:51Z", "points": 8675}, {"id": 9537088, "course_id": 83500, "map_id": 835, "map_name": "kz_symmetry", "map_stage": 0, "stage_tier": 2, "steam_id": "STEAM_1:1:122301121", "player_name": "Kuupo", "mode": "kz_timer", "time": 151.008, "teleports": 0, "created_on": "2020-12-18T17:14:34Z", "points": 8674}, {"id": 11586157, "course_id": 83500, "map_id": 835, "map_name": "kz_symmetry", "map_stage": 0, "stage_tier": 2, "steam_id": "STEAM_1:1:24049284", "player_name": "Harry_Pootha", "mode": "kz_timer", "time": 151.406, "teleports": 0, "created_on": "2021-04-09T16:03:20Z", "points": 8672}, {"id": 8395049, "course_id": 83500, "map_id": 835, "map_name": "kz_symmetry", "map_stage": 0, "stage_tier": 2, "steam_id": "STEAM_1:1:118775164", "player_name": "desertation", "mode": "kz_timer", "time": 155.352, "teleports": 0, "created_on": "2020-10-01T15:22:00Z", "points": 8660}, {"id": 21595916, "course_id": 83500, "map_id": 835, "map_name": "kz_symmetry", "map_stage": 0, "stage_tier": 2, "steam_id": "STEAM_1:0:63050232", "player_name": "oldgt25", "mode": "kz_timer", "time": 156.039, "teleports": 0, "created_on": "2023-06-04T20:16:54Z", "points": 8658}, {"id": 8057205, "course_id": 83500, "map_id": 835, "map_name": "kz_symmetry", "map_stage": 0, "stage_tier": 2, "steam_id": "STEAM_1:0:46512478", "player_name": "Dostoyevsky", "mode": "kz_timer", "time": 156.5, "teleports": 0, "created_on": "2020-09-09T15:36:00Z", "points": 8657}, {"id": 8267798, "course_id": 83500, "map_id": 835, "map_name": "kz_symmetry", "map_stage": 0, "stage_tier": 2, "steam_id": "STEAM_1:0:146371948", "player_name": "stun. but stoned", "mode": "kz_timer", "time": 160.281, "teleports": 0, "created_on": "2020-09-22T20:53:33Z", "points": 8645}, {"id": 8090615, "course_id": 83500, "map_id": 835, "map_name": "kz_symmetry", "map_stage": 0, "stage_tier": 2, "steam_id": "STEAM_1:0:482074794", "player_name": "Niksu", "mode": "kz_timer", "time": 161.984, "teleports": 0, "created_on": "2020-09-11T15:21:27Z", "points": 8640}, {"id": 11580458, "course_id": 83500, "map_id": 835, "map_name": "kz_symmetry", "map_stage": 0, "stage_tier": 2, "steam_id": "STEAM_1:1:29129528", "player_name": "Purkkilo", "mode": "kz_timer", "time": 166.266, "teleports": 0, "created_on": "2021-04-09T11:13:40Z", "points": 8624}, {"id": 8239038, "course_id": 83500, "map_id": 835, "map_name": "kz_symmetry", "map_stage": 0, "stage_tier": 2, "steam_id": "STEAM_1:1:16411902", "player_name": "VertikO", "mode": "kz_timer", "time": 166.359, "teleports": 0, "created_on": "2020-09-20T21:34:12Z", "points": 8624}, {"id": 13959265, "course_id": 83500, "map_id": 835, "map_name": "kz_symmetry", "map_stage": 0, "stage_tier": 2, "steam_id": "STEAM_1:0:54911203", "player_name": "hhz", "mode": "kz_timer", "time": 168.031, "teleports": 0, "created_on": "2021-10-09T23:28:30Z", "points": 8618}, {"id": 12755668, "course_id": 83500, "map_id": 835, "map_name": "kz_symmetry", "map_stage": 0, "stage_tier": 2, "steam_id": "STEAM_1:1:122415973", "player_name": "\u044f [\u0441\u0430\u0448\u0430 | \u043f\u0430\u043c\u043f\u0435\u0440\u0441]", "mode": "kz_timer", "time": 169.297, "teleports": 0, "created_on": "2021-06-23T00:13:15Z", "points": 8614}, {"id": 15074391, "course_id": 83500, "map_id": 835, "map_name": "kz_symmetry", "map_stage": 0, "stage_tier": 2, "steam_id": "STEAM_1:1:168575119", "player_name": "Flonnych", "mode": "kz_timer", "time": 170.18, "teleports": 0, "created_on": "2022-01-24T13:16:45Z", "points": 8611}, {"id": 12507414, "course_id": 83500, "map_id": 835, "map_name": "kz_symmetry", "map_stage": 0, "stage_tier": 2, "steam_id": "STEAM_1:0:510052581", "player_name": "Kebab 101", "mode": "kz_timer", "time": 172.852, "teleports": 0, "created_on": "2021-06-04T15:03:51Z", "points": 8602}, {"id": 8079102, "course_id": 83500, "map_id": 835, "map_name": "kz_symmetry", "map_stage": 0, "stage_tier": 2, "steam_id": "STEAM_1:1:119162181", "player_name": "\u300cPRoZZoR\u300d", "mode": "kz_timer", "time": 175.094, "teleports": 0, "created_on": "2020-09-10T21:45:43Z", "points": 8592}, {"id": 10115630, "course_id": 83500, "map_id": 835, "map_name": "kz_symmetry", "map_stage": 0, "stage_tier": 2, "steam_id": "STEAM_1:0:99996809", "player_name": "downeel", "mode": "kz_timer", "time": 175.258, "teleports": 0, "created_on": "2021-01-20T15:47:52Z", "points": 8592}, {"id": 13948917, "course_id": 83500, "map_id": 835, "map_name": "kz_symmetry", "map_stage": 0, "stage_tier": 2, "steam_id": "STEAM_1:0:173330978", "player_name": "damo", "mode": "kz_timer", "time": 175.797, "teleports": 0, "created_on": "2021-10-09T00:47:38Z", "points": 8589}, {"id": 8047244, "course_id": 83500, "map_id": 835, "map_name": "kz_symmetry", "map_stage": 0, "stage_tier": 2, "steam_id": "STEAM_1:0:139110918", "player_name": "Raswein", "mode": "kz_timer", "time": 178.274, "teleports": 0, "created_on": "2020-09-09T00:55:53Z", "points": 8580}, {"id": 10847666, "course_id": 83500, "map_id": 835, "map_name": "kz_symmetry", "map_stage": 0, "stage_tier": 2, "steam_id": "STEAM_1:1:42177236", "player_name": "lymbo", "mode": "kz_timer", "time": 180.024, "teleports": 0, "created_on": "2021-03-01T02:45:43Z", "points": 8574}, {"id": 16506775, "course_id": 83500, "map_id": 835, "map_name": "kz_symmetry", "map_stage": 0, "stage_tier": 2, "steam_id": "STEAM_1:1:37733491", "player_name": "xane", "mode": "kz_timer", "time": 181.773, "teleports": 0, "created_on": "2022-05-18T15:22:10Z", "points": 8566}, {"id": 11863131, "course_id": 83500, "map_id": 835, "map_name": "kz_symmetry", "map_stage": 0, "stage_tier": 2, "steam_id": "STEAM_1:1:95067393", "player_name": "Motimake ;)", "mode": "kz_timer", "time": 186.383, "teleports": 0, "created_on": "2021-04-24T21:46:08Z", "points": 8549}, {"id": 10882390, "course_id": 83500, "map_id": 835, "map_name": "kz_symmetry", "map_stage": 0, "stage_tier": 2, "steam_id": "STEAM_1:1:446956509", "player_name": "asraf", "mode": "kz_timer", "time": 187.305, "teleports": 0, "created_on": "2021-03-02T21:34:05Z", "points": 8545}, {"id": 21595928, "course_id": 83500, "map_id": 835, "map_name": "kz_symmetry", "map_stage": 0, "stage_tier": 2, "steam_id": "STEAM_1:1:526648385", "player_name": "Fry", "mode": "kz_timer", "time": 192.203, "teleports": 0, "created_on": "2023-06-04T20:18:06Z", "points": 8526}, {"id": 8108151, "course_id": 83500, "map_id": 835, "map_name": "kz_symmetry", "map_stage": 0, "stage_tier": 2, "steam_id": "STEAM_1:0:142871078", "player_name": "3 fortnite vbucks", "mode": "kz_timer", "time": 193.758, "teleports": 0, "created_on": "2020-09-12T15:53:51Z", "points": 8518}, {"id": 9051102, "course_id": 83500, "map_id": 835, "map_name": "kz_symmetry", "map_stage": 0, "stage_tier": 2, "steam_id": "STEAM_1:0:208549572", "player_name": "AnttuS", "mode": "kz_timer", "time": 194.297, "teleports": 0, "created_on": "2020-11-17T02:51:50Z", "points": 8515}, {"id": 10115436, "course_id": 83500, "map_id": 835, "map_name": "kz_symmetry", "map_stage": 0, "stage_tier": 2, "steam_id": "STEAM_1:0:58420135", "player_name": "Hortt", "mode": "kz_timer", "time": 197.328, "teleports": 0, "created_on": "2021-01-20T15:35:21Z", "points": 8502}, {"id": 12487879, "course_id": 83500, "map_id": 835, "map_name": "kz_symmetry", "map_stage": 0, "stage_tier": 2, "steam_id": "STEAM_1:1:91436052", "player_name": "STME", "mode": "kz_timer", "time": 200.039, "teleports": 0, "created_on": "2021-06-03T06:23:19Z", "points": 8490}, {"id": 10698309, "course_id": 83500, "map_id": 835, "map_name": "kz_symmetry", "map_stage": 0, "stage_tier": 2, "steam_id": "STEAM_1:1:528944830", "player_name": "3xx_EnderMix", "mode": "kz_timer", "time": 200.654, "teleports": 0, "created_on": "2021-02-21T10:49:47Z", "points": 8487}, {"id": 8828021, "course_id": 83500, "map_id": 835, "map_name": "kz_symmetry", "map_stage": 0, "stage_tier": 2, "steam_id": "STEAM_1:0:55972459", "player_name": "Fafnir", "mode": "kz_timer", "time": 201.305, "teleports": 0, "created_on": "2020-11-01T08:26:16Z", "points": 8484}, {"id": 10847436, "course_id": 83500, "map_id": 835, "map_name": "kz_symmetry", "map_stage": 0, "stage_tier": 2, "steam_id": "STEAM_1:0:64269053", "player_name": "yoseph", "mode": "kz_timer", "time": 202.586, "teleports": 0, "created_on": "2021-03-01T02:18:56Z", "points": 8479}, {"id": 8078307, "course_id": 83500, "map_id": 835, "map_name": "kz_symmetry", "map_stage": 0, "stage_tier": 2, "steam_id": "STEAM_1:1:17676543", "player_name": "Gurylla", "mode": "kz_timer", "time": 205.547, "teleports": 0, "created_on": "2020-09-10T20:50:43Z", "points": 8464}, {"id": 9696710, "course_id": 83500, "map_id": 835, "map_name": "kz_symmetry", "map_stage": 0, "stage_tier": 2, "steam_id": "STEAM_1:1:79287752", "player_name": "Lami", "mode": "kz_timer", "time": 208.445, "teleports": 0, "created_on": "2020-12-28T01:09:21Z", "points": 8450}, {"id": 11311206, "course_id": 83500, "map_id": 835, "map_name": "kz_symmetry", "map_stage": 0, "stage_tier": 2, "steam_id": "STEAM_1:1:220110903", "player_name": "QuiZpexX-", "mode": "kz_timer", "time": 210.953, "teleports": 0, "created_on": "2021-03-25T19:18:07Z", "points": 8437}, {"id": 8269320, "course_id": 83500, "map_id": 835, "map_name": "kz_symmetry", "map_stage": 0, "stage_tier": 2, "steam_id": "STEAM_1:0:50615596", "player_name": "nobus", "mode": "kz_timer", "time": 211.275, "teleports": 0, "created_on": "2020-09-22T23:00:23Z", "points": 8435}, {"id": 16806759, "course_id": 83500, "map_id": 835, "map_name": "kz_symmetry", "map_stage": 0, "stage_tier": 2, "steam_id": "STEAM_1:1:84136763", "player_name": "fee", "mode": "kz_timer", "time": 211.367, "teleports": 0, "created_on": "2022-06-11T16:52:35Z", "points": 8435}, {"id": 14947620, "course_id": 83500, "map_id": 835, "map_name": "kz_symmetry", "map_stage": 0, "stage_tier": 2, "steam_id": "STEAM_1:0:45231154", "player_name": "brad", "mode": "kz_timer", "time": 212.867, "teleports": 0, "created_on": "2022-01-14T01:38:48Z", "points": 8428}, {"id": 16575965, "course_id": 83500, "map_id": 835, "map_name": "kz_symmetry", "map_stage": 0, "stage_tier": 2, "steam_id": "STEAM_1:0:452534871", "player_name": "longzhmm63", "mode": "kz_timer", "time": 215.234, "teleports": 0, "created_on": "2022-05-24T06:09:13Z", "points": 8416}, {"id": 21438273, "course_id": 83500, "map_id": 835, "map_name": "kz_symmetry", "map_stage": 0, "stage_tier": 2, "steam_id": "STEAM_1:0:429143623", "player_name": "Divixx\u2122", "mode": "kz_timer", "time": 217.758, "teleports": 0, "created_on": "2023-05-26T21:58:06Z", "points": 8403}, {"id": 8026844, "course_id": 83500, "map_id": 835, "map_name": "kz_symmetry", "map_stage": 0, "stage_tier": 2, "steam_id": "STEAM_1:1:116656647", "player_name": "wiunx", "mode": "kz_timer", "time": 218.219, "teleports": 0, "created_on": "2020-09-07T23:34:54Z", "points": 8401}, {"id": 8611699, "course_id": 83500, "map_id": 835, "map_name": "kz_symmetry", "map_stage": 0, "stage_tier": 2, "steam_id": "STEAM_1:0:18220375", "player_name": "funkerman", "mode": "kz_timer", "time": 220.305, "teleports": 0, "created_on": "2020-10-17T01:20:07Z", "points": 8391}, {"id": 8021562, "course_id": 83500, "map_id": 835, "map_name": "kz_symmetry", "map_stage": 0, "stage_tier": 2, "steam_id": "STEAM_1:1:165021693", "player_name": "soak", "mode": "kz_timer", "time": 226.617, "teleports": 0, "created_on": "2020-09-07T18:35:58Z", "points": 8358}, {"id": 8806844, "course_id": 83500, "map_id": 835, "map_name": "kz_symmetry", "map_stage": 0, "stage_tier": 2, "steam_id": "STEAM_1:0:122816464", "player_name": "GiimPy", "mode": "kz_timer", "time": 227.016, "teleports": 0, "created_on": "2020-10-30T23:01:57Z", "points": 8356}, {"id": 21855920, "course_id": 83500, "map_id": 835, "map_name": "kz_symmetry", "map_stage": 0, "stage_tier": 2, "steam_id": "STEAM_1:1:450009297", "player_name": "lilmar1", "mode": "kz_timer", "time": 229.668, "teleports": 0, "created_on": "2023-06-19T23:37:14Z", "points": 8341}, {"id": 14189655, "course_id": 83500, "map_id": 835, "map_name": "kz_symmetry", "map_stage": 0, "stage_tier": 2, "steam_id": "STEAM_1:0:10663671", "player_name": "\ud5c8\uc811", "mode": "kz_timer", "time": 229.781, "teleports": 0, "created_on": "2021-11-02T05:48:26Z", "points": 8341}, {"id": 20627355, "course_id": 83500, "map_id": 835, "map_name": "kz_symmetry", "map_stage": 0, "stage_tier": 2, "steam_id": "STEAM_1:0:40278378", "player_name": "(\u25d5\u203f\u25d5)", "mode": "kz_timer", "time": 231.515, "teleports": 0, "created_on": "2023-04-07T22:07:18Z", "points": 8331}, {"id": 8347198, "course_id": 83500, "map_id": 835, "map_name": "kz_symmetry", "map_stage": 0, "stage_tier": 2, "steam_id": "STEAM_1:0:509934308", "player_name": "ambi", "mode": "kz_timer", "time": 231.594, "teleports": 0, "created_on": "2020-09-28T07:15:29Z", "points": 8331}, {"id": 9593248, "course_id": 83500, "map_id": 835, "map_name": "kz_symmetry", "map_stage": 0, "stage_tier": 2, "steam_id": "STEAM_1:1:233884846", "player_name": "Hawk", "mode": "kz_timer", "time": 236.453, "teleports": 0, "created_on": "2020-12-21T22:09:29Z", "points": 8302}, {"id": 17625785, "course_id": 83500, "map_id": 835, "map_name": "kz_symmetry", "map_stage": 0, "stage_tier": 2, "steam_id": "STEAM_1:0:88029774", "player_name": "\u6cd5\u56fd\u9762\u5305", "mode": "kz_timer", "time": 237.172, "teleports": 0, "created_on": "2022-08-12T15:57:44Z", "points": 8298}, {"id": 16771858, "course_id": 83500, "map_id": 835, "map_name": "kz_symmetry", "map_stage": 0, "stage_tier": 2, "steam_id": "STEAM_1:1:559225712", "player_name": "avalon", "mode": "kz_timer", "time": 240.313, "teleports": 0, "created_on": "2022-06-09T01:04:44Z", "points": 8280}, {"id": 10430729, "course_id": 83500, "map_id": 835, "map_name": "kz_symmetry", "map_stage": 0, "stage_tier": 2, "steam_id": "STEAM_1:1:45935626", "player_name": "Skyater", "mode": "kz_timer", "time": 242.691, "teleports": 0, "created_on": "2021-02-06T23:02:02Z", "points": 8265}, {"id": 8285703, "course_id": 83500, "map_id": 835, "map_name": "kz_symmetry", "map_stage": 0, "stage_tier": 2, "steam_id": "STEAM_1:1:123487235", "player_name": "dynamic", "mode": "kz_timer", "time": 246.875, "teleports": 0, "created_on": "2020-09-24T01:13:04Z", "points": 8239}, {"id": 8088317, "course_id": 83500, "map_id": 835, "map_name": "kz_symmetry", "map_stage": 0, "stage_tier": 2, "steam_id": "STEAM_1:0:36339773", "player_name": "MY DOGS NAME IS VIIMA", "mode": "kz_timer", "time": 247.813, "teleports": 0, "created_on": "2020-09-11T12:42:19Z", "points": 8233}, {"id": 8040746, "course_id": 83500, "map_id": 835, "map_name": "kz_symmetry", "map_stage": 0, "stage_tier": 2, "steam_id": "STEAM_1:1:51369212", "player_name": "Katten", "mode": "kz_timer", "time": 249.32, "teleports": 0, "created_on": "2020-09-08T16:44:15Z", "points": 8223}, {"id": 16154903, "course_id": 83500, "map_id": 835, "map_name": "kz_symmetry", "map_stage": 0, "stage_tier": 2, "steam_id": "STEAM_1:1:117268758", "player_name": "neon", "mode": "kz_timer", "time": 252.578, "teleports": 0, "created_on": "2022-04-21T10:29:24Z", "points": 8202}, {"id": 8026875, "course_id": 83500, "map_id": 835, "map_name": "kz_symmetry", "map_stage": 0, "stage_tier": 2, "steam_id": "STEAM_1:0:29122831", "player_name": "Boux", "mode": "kz_timer", "time": 252.633, "teleports": 0, "created_on": "2020-09-07T23:36:42Z", "points": 8201}, {"id": 18423264, "course_id": 83500, "map_id": 835, "map_name": "kz_symmetry", "map_stage": 0, "stage_tier": 2, "steam_id": "STEAM_1:0:125378604", "player_name": "fRaZzT6 #RATTLESNAKE", "mode": "kz_timer", "time": 254.281, "teleports": 0, "created_on": "2022-10-05T19:25:09Z", "points": 8190}, {"id": 15879922, "course_id": 83500, "map_id": 835, "map_name": "kz_symmetry", "map_stage": 0, "stage_tier": 2, "steam_id": "STEAM_1:1:121779585", "player_name": "Rumble", "mode": "kz_timer", "time": 257.563, "teleports": 0, "created_on": "2022-03-29T14:11:13Z", "points": 8169}, {"id": 8137985, "course_id": 83500, "map_id": 835, "map_name": "kz_symmetry", "map_stage": 0, "stage_tier": 2, "steam_id": "STEAM_1:1:199480275", "player_name": "Yikk__", "mode": "kz_timer", "time": 262.434, "teleports": 0, "created_on": "2020-09-14T11:08:56Z", "points": 8136}, {"id": 8056559, "course_id": 83500, "map_id": 835, "map_name": "kz_symmetry", "map_stage": 0, "stage_tier": 2, "steam_id": "STEAM_1:1:58874509", "player_name": "iBUYFL0WER Burgit", "mode": "kz_timer", "time": 263.203, "teleports": 0, "created_on": "2020-09-09T14:56:28Z", "points": 8130}, {"id": 8051435, "course_id": 83500, "map_id": 835, "map_name": "kz_symmetry", "map_stage": 0, "stage_tier": 2, "steam_id": "STEAM_1:0:154628481", "player_name": "Veeky", "mode": "kz_timer", "time": 263.453, "teleports": 0, "created_on": "2020-09-09T08:25:03Z", "points": 8128}, {"id": 10430194, "course_id": 83500, "map_id": 835, "map_name": "kz_symmetry", "map_stage": 0, "stage_tier": 2, "steam_id": "STEAM_1:1:432489263", "player_name": "asd", "mode": "kz_timer", "time": 263.461, "teleports": 0, "created_on": "2021-02-06T22:25:12Z", "points": 8128}, {"id": 15636666, "course_id": 83500, "map_id": 835, "map_name": "kz_symmetry", "map_stage": 0, "stage_tier": 2, "steam_id": "STEAM_1:1:100652135", "player_name": "Daniel", "mode": "kz_timer", "time": 264.609, "teleports": 0, "created_on": "2022-03-10T23:47:04Z", "points": 8120}, {"id": 8722306, "course_id": 83500, "map_id": 835, "map_name": "kz_symmetry", "map_stage": 0, "stage_tier": 2, "steam_id": "STEAM_1:0:235211777", "player_name": "sooyaa", "mode": "kz_timer", "time": 264.883, "teleports": 0, "created_on": "2020-10-25T02:23:02Z", "points": 8117}, {"id": 12001285, "course_id": 83500, "map_id": 835, "map_name": "kz_symmetry", "map_stage": 0, "stage_tier": 2, "steam_id": "STEAM_1:0:47709052", "player_name": "Nande? Ka[X]de!", "mode": "kz_timer", "time": 266.334, "teleports": 0, "created_on": "2021-05-03T11:29:33Z", "points": 8106}, {"id": 14540156, "course_id": 83500, "map_id": 835, "map_name": "kz_symmetry", "map_stage": 0, "stage_tier": 2, "steam_id": "STEAM_1:1:31653734", "player_name": "Ebun", "mode": "kz_timer", "time": 267.133, "teleports": 0, "created_on": "2021-12-07T00:50:03Z", "points": 8101}, {"id": 22879744, "course_id": 83500, "map_id": 835, "map_name": "kz_symmetry", "map_stage": 0, "stage_tier": 2, "steam_id": "STEAM_1:0:59969911", "player_name": "BETT5R", "mode": "kz_timer", "time": 267.297, "teleports": 0, "created_on": "2023-08-28T23:36:32Z", "points": 8100}, {"id": 22374204, "course_id": 83500, "map_id": 835, "map_name": "kz_symmetry", "map_stage": 0, "stage_tier": 2, "steam_id": "STEAM_1:1:123513682", "player_name": "Lester", "mode": "kz_timer", "time": 268.18, "teleports": 0, "created_on": "2023-07-26T14:51:22Z", "points": 8094}, {"id": 17855443, "course_id": 83500, "map_id": 835, "map_name": "kz_symmetry", "map_stage": 0, "stage_tier": 2, "steam_id": "STEAM_1:1:55230187", "player_name": "Ed", "mode": "kz_timer", "time": 270.023, "teleports": 0, "created_on": "2022-08-27T21:17:05Z", "points": 8081}, {"id": 8035976, "course_id": 83500, "map_id": 835, "map_name": "kz_symmetry", "map_stage": 0, "stage_tier": 2, "steam_id": "STEAM_1:1:118898580", "player_name": "Dima", "mode": "kz_timer", "time": 271.789, "teleports": 0, "created_on": "2020-09-08T11:50:39Z", "points": 8069}, {"id": 15016670, "course_id": 83500, "map_id": 835, "map_name": "kz_symmetry", "map_stage": 0, "stage_tier": 2, "steam_id": "STEAM_1:0:603420995", "player_name": "\u0442\u0430\u043c \u0433\u0434\u0435 wasd", "mode": "kz_timer", "time": 272.094, "teleports": 0, "created_on": "2022-01-19T18:57:12Z", "points": 8067}, {"id": 13363456, "course_id": 83500, "map_id": 835, "map_name": "kz_symmetry", "map_stage": 0, "stage_tier": 2, "steam_id": "STEAM_1:1:101035890", "player_name": "Bonari", "mode": "kz_timer", "time": 279.07, "teleports": 0, "created_on": "2021-08-17T14:51:31Z", "points": 8019}, {"id": 13849864, "course_id": 83500, "map_id": 835, "map_name": "kz_symmetry", "map_stage": 0, "stage_tier": 2, "steam_id": "STEAM_1:1:97984616", "player_name": "spaghetti senpai", "mode": "kz_timer", "time": 284.227, "teleports": 0, "created_on": "2021-09-29T04:50:05Z", "points": 7983}, {"id": 8049118, "course_id": 83500, "map_id": 835, "map_name": "kz_symmetry", "map_stage": 0, "stage_tier": 2, "steam_id": "STEAM_1:0:78548159", "player_name": "GMZ", "mode": "kz_timer", "time": 284.695, "teleports": 0, "created_on": "2020-09-09T03:52:04Z", "points": 7979}, {"id": 8356297, "course_id": 83500, "map_id": 835, "map_name": "kz_symmetry", "map_stage": 0, "stage_tier": 2, "steam_id": "STEAM_1:1:24488250", "player_name": "jank\u263a", "mode": "kz_timer", "time": 286.477, "teleports": 0, "created_on": "2020-09-28T21:06:07Z", "points": 7966}, {"id": 17681539, "course_id": 83500, "map_id": 835, "map_name": "kz_symmetry", "map_stage": 0, "stage_tier": 2, "steam_id": "STEAM_1:1:97870647", "player_name": "Christian Missionary", "mode": "kz_timer", "time": 286.695, "teleports": 0, "created_on": "2022-08-16T03:01:42Z", "points": 7965}, {"id": 9678752, "course_id": 83500, "map_id": 835, "map_name": "kz_symmetry", "map_stage": 0, "stage_tier": 2, "steam_id": "STEAM_1:0:99325120", "player_name": "Samm35", "mode": "kz_timer", "time": 288.836, "teleports": 0, "created_on": "2020-12-26T23:20:56Z", "points": 7949}, {"id": 11950368, "course_id": 83500, "map_id": 835, "map_name": "kz_symmetry", "map_stage": 0, "stage_tier": 2, "steam_id": "STEAM_1:1:153932807", "player_name": "spomiaselucasimol", "mode": "kz_timer", "time": 290.359, "teleports": 0, "created_on": "2021-04-30T06:03:43Z", "points": 7937}, {"id": 16327537, "course_id": 83500, "map_id": 835, "map_name": "kz_symmetry", "map_stage": 0, "stage_tier": 2, "steam_id": "STEAM_1:0:129656982", "player_name": "KaKa47", "mode": "kz_timer", "time": 294.859, "teleports": 0, "created_on": "2022-05-04T15:36:20Z", "points": 7904}, {"id": 16734899, "course_id": 83500, "map_id": 835, "map_name": "kz_symmetry", "map_stage": 0, "stage_tier": 2, "steam_id": "STEAM_1:1:26423367", "player_name": "k one", "mode": "kz_timer", "time": 295.563, "teleports": 0, "created_on": "2022-06-06T10:12:46Z", "points": 7898}, {"id": 8056394, "course_id": 83500, "map_id": 835, "map_name": "kz_symmetry", "map_stage": 0, "stage_tier": 2, "steam_id": "STEAM_1:1:89886117", "player_name": "rapu chan", "mode": "kz_timer", "time": 296.406, "teleports": 0, "created_on": "2020-09-09T14:46:09Z", "points": 7892}, {"id": 20929799, "course_id": 83500, "map_id": 835, "map_name": "kz_symmetry", "map_stage": 0, "stage_tier": 2, "steam_id": "STEAM_1:0:64490802", "player_name": "Kestojuusto2", "mode": "kz_timer", "time": 298.594, "teleports": 0, "created_on": "2023-04-23T12:15:25Z", "points": 7875}, {"id": 8087092, "course_id": 83500, "map_id": 835, "map_name": "kz_symmetry", "map_stage": 0, "stage_tier": 2, "steam_id": "STEAM_1:1:105191775", "player_name": "Robbani q:-D", "mode": "kz_timer", "time": 301.531, "teleports": 0, "created_on": "2020-09-11T11:09:43Z", "points": 7852}, {"id": 20260490, "course_id": 83500, "map_id": 835, "map_name": "kz_symmetry", "map_stage": 0, "stage_tier": 2, "steam_id": "STEAM_1:1:727974807", "player_name": "june!", "mode": "kz_timer", "time": 302.148, "teleports": 0, "created_on": "2023-03-19T05:23:02Z", "points": 7847}, {"id": 10894408, "course_id": 83500, "map_id": 835, "map_name": "kz_symmetry", "map_stage": 0, "stage_tier": 2, "steam_id": "STEAM_1:0:210927467", "player_name": "mex", "mode": "kz_timer", "time": 302.569, "teleports": 0, "created_on": "2021-03-03T15:33:31Z", "points": 7844}, {"id": 11794699, "course_id": 83500, "map_id": 835, "map_name": "kz_symmetry", "map_stage": 0, "stage_tier": 2, "steam_id": "STEAM_1:0:32642796", "player_name": "s4mpl", "mode": "kz_timer", "time": 304.801, "teleports": 0, "created_on": "2021-04-21T00:05:35Z", "points": 7826}, {"id": 8776654, "course_id": 83500, "map_id": 835, "map_name": "kz_symmetry", "map_stage": 0, "stage_tier": 2, "steam_id": "STEAM_1:1:70975081", "player_name": "\ud835\udca5\ud835\udcca\ud835\udcbe\ud835\udcc8\ud835\udcc8\ud835\udcbe", "mode": "kz_timer", "time": 305.438, "teleports": 0, "created_on": "2020-10-29T00:47:22Z", "points": 7821}, {"id": 20265289, "course_id": 83500, "map_id": 835, "map_name": "kz_symmetry", "map_stage": 0, "stage_tier": 2, "steam_id": "STEAM_1:1:33706702", "player_name": "\u6597\u72d7", "mode": "kz_timer", "time": 307.883, "teleports": 0, "created_on": "2023-03-19T11:31:10Z", "points": 7801}, {"id": 15079192, "course_id": 83500, "map_id": 835, "map_name": "kz_symmetry", "map_stage": 0, "stage_tier": 2, "steam_id": "STEAM_1:1:160732927", "player_name": "-wesenS*", "mode": "kz_timer", "time": 308.891, "teleports": 0, "created_on": "2022-01-24T20:23:42Z", "points": 7793}, {"id": 8677971, "course_id": 83500, "map_id": 835, "map_name": "kz_symmetry", "map_stage": 0, "stage_tier": 2, "steam_id": "STEAM_1:0:108123829", "player_name": "brandon", "mode": "kz_timer", "time": 314.271, "teleports": 0, "created_on": "2020-10-22T00:46:09Z", "points": 7752}, {"id": 11637415, "course_id": 83500, "map_id": 835, "map_name": "kz_symmetry", "map_stage": 0, "stage_tier": 2, "steam_id": "STEAM_1:0:162326871", "player_name": "lulle", "mode": "kz_timer", "time": 315.031, "teleports": 0, "created_on": "2021-04-12T08:11:18Z", "points": 7746}, {"id": 8043664, "course_id": 83500, "map_id": 835, "map_name": "kz_symmetry", "map_stage": 0, "stage_tier": 2, "steam_id": "STEAM_1:1:64024647", "player_name": "pentaminum", "mode": "kz_timer", "time": 321.676, "teleports": 0, "created_on": "2020-09-08T19:45:18Z", "points": 7691}, {"id": 9642899, "course_id": 83500, "map_id": 835, "map_name": "kz_symmetry", "map_stage": 0, "stage_tier": 2, "steam_id": "STEAM_1:1:450433075", "player_name": "IcyBox", "mode": "kz_timer", "time": 323.258, "teleports": 0, "created_on": "2020-12-24T19:33:33Z", "points": 7679}, {"id": 17895146, "course_id": 83500, "map_id": 835, "map_name": "kz_symmetry", "map_stage": 0, "stage_tier": 2, "steam_id": "STEAM_1:1:605441756", "player_name": "991ts", "mode": "kz_timer", "time": 325.758, "teleports": 0, "created_on": "2022-08-30T14:04:04Z", "points": 7658}, {"id": 8073859, "course_id": 83500, "map_id": 835, "map_name": "kz_symmetry", "map_stage": 0, "stage_tier": 2, "steam_id": "STEAM_1:1:50261787", "player_name": "\u2605 Karbouner", "mode": "kz_timer", "time": 327.414, "teleports": 0, "created_on": "2020-09-10T15:20:38Z", "points": 7643}, {"id": 10847481, "course_id": 83500, "map_id": 835, "map_name": "kz_symmetry", "map_stage": 0, "stage_tier": 2, "steam_id": "STEAM_1:1:183023126", "player_name": "seungcheol baek", "mode": "kz_timer", "time": 334.813, "teleports": 0, "created_on": "2021-03-01T02:24:51Z", "points": 7581}, {"id": 14647612, "course_id": 83500, "map_id": 835, "map_name": "kz_symmetry", "map_stage": 0, "stage_tier": 2, "steam_id": "STEAM_1:0:537150442", "player_name": "KefurASS", "mode": "kz_timer", "time": 336.156, "teleports": 0, "created_on": "2021-12-17T10:00:53Z", "points": 7570}, {"id": 8021663, "course_id": 83500, "map_id": 835, "map_name": "kz_symmetry", "map_stage": 0, "stage_tier": 2, "steam_id": "STEAM_1:0:45778590", "player_name": "HellzAlien", "mode": "kz_timer", "time": 337.117, "teleports": 0, "created_on": "2020-09-07T18:41:22Z", "points": 7562}, {"id": 9916534, "course_id": 83500, "map_id": 835, "map_name": "kz_symmetry", "map_stage": 0, "stage_tier": 2, "steam_id": "STEAM_1:1:116739970", "player_name": "M u g e n", "mode": "kz_timer", "time": 339.672, "teleports": 0, "created_on": "2021-01-09T19:27:10Z", "points": 7539}, {"id": 9585454, "course_id": 83500, "map_id": 835, "map_name": "kz_symmetry", "map_stage": 0, "stage_tier": 2, "steam_id": "STEAM_1:0:44574375", "player_name": "farru", "mode": "kz_timer", "time": 341.272, "teleports": 0, "created_on": "2020-12-21T14:51:39Z", "points": 7525}, {"id": 8026929, "course_id": 83500, "map_id": 835, "map_name": "kz_symmetry", "map_stage": 0, "stage_tier": 2, "steam_id": "STEAM_1:1:532273515", "player_name": "PaaVo", "mode": "kz_timer", "time": 344.141, "teleports": 0, "created_on": "2020-09-07T23:39:15Z", "points": 7501}, {"id": 17895311, "course_id": 83500, "map_id": 835, "map_name": "kz_symmetry", "map_stage": 0, "stage_tier": 2, "steam_id": "STEAM_1:0:192021312", "player_name": "Wr1ght", "mode": "kz_timer", "time": 346.102, "teleports": 0, "created_on": "2022-08-30T14:14:11Z", "points": 7484}, {"id": 16576162, "course_id": 83500, "map_id": 835, "map_name": "kz_symmetry", "map_stage": 0, "stage_tier": 2, "steam_id": "STEAM_1:1:93950977", "player_name": "deef", "mode": "kz_timer", "time": 352.856, "teleports": 0, "created_on": "2022-05-24T06:37:51Z", "points": 7426}, {"id": 15975113, "course_id": 83500, "map_id": 835, "map_name": "kz_symmetry", "map_stage": 0, "stage_tier": 2, "steam_id": "STEAM_1:1:224821831", "player_name": "ShallowDream", "mode": "kz_timer", "time": 355.738, "teleports": 0, "created_on": "2022-04-07T04:18:15Z", "points": 7401}, {"id": 8078457, "course_id": 83500, "map_id": 835, "map_name": "kz_symmetry", "map_stage": 0, "stage_tier": 2, "steam_id": "STEAM_1:1:21172591", "player_name": "d1rTy*S", "mode": "kz_timer", "time": 364.352, "teleports": 0, "created_on": "2020-09-10T20:59:32Z", "points": 7322}, {"id": 18601799, "course_id": 83500, "map_id": 835, "map_name": "kz_symmetry", "map_stage": 0, "stage_tier": 2, "steam_id": "STEAM_1:1:15311003", "player_name": "GOA", "mode": "kz_timer", "time": 373.016, "teleports": 0, "created_on": "2022-10-21T13:47:46Z", "points": 7245}, {"id": 10555080, "course_id": 83500, "map_id": 835, "map_name": "kz_symmetry", "map_stage": 0, "stage_tier": 2, "steam_id": "STEAM_1:0:456007178", "player_name": "Koksu", "mode": "kz_timer", "time": 375.375, "teleports": 0, "created_on": "2021-02-13T17:21:41Z", "points": 7222}, {"id": 15879821, "course_id": 83500, "map_id": 835, "map_name": "kz_symmetry", "map_stage": 0, "stage_tier": 2, "steam_id": "STEAM_1:0:61930606", "player_name": "drink ur own piss", "mode": "kz_timer", "time": 375.578, "teleports": 0, "created_on": "2022-03-29T14:04:59Z", "points": 7220}, {"id": 11292697, "course_id": 83500, "map_id": 835, "map_name": "kz_symmetry", "map_stage": 0, "stage_tier": 2, "steam_id": "STEAM_1:0:458349110", "player_name": "Broken Promises", "mode": "kz_timer", "time": 376.805, "teleports": 0, "created_on": "2021-03-24T21:10:19Z", "points": 7209}, {"id": 19357144, "course_id": 83500, "map_id": 835, "map_name": "kz_symmetry", "map_stage": 0, "stage_tier": 2, "steam_id": "STEAM_1:1:451523417", "player_name": "\u653e\u4e0b\u4f60\u624b\u4e2d\u7684\u9488\u7ebf\u6d3b", "mode": "kz_timer", "time": 378.992, "teleports": 0, "created_on": "2022-12-27T09:32:17Z", "points": 7188}, {"id": 8032476, "course_id": 83500, "map_id": 835, "map_name": "kz_symmetry", "map_stage": 0, "stage_tier": 2, "steam_id": "STEAM_1:0:51560588", "player_name": "y3f", "mode": "kz_timer", "time": 379.047, "teleports": 0, "created_on": "2020-09-08T06:31:12Z", "points": 7188}, {"id": 17681682, "course_id": 83500, "map_id": 835, "map_name": "kz_symmetry", "map_stage": 0, "stage_tier": 2, "steam_id": "STEAM_1:1:13368494", "player_name": "3dou", "mode": "kz_timer", "time": 380.09, "teleports": 0, "created_on": "2022-08-16T03:17:48Z", "points": 7179}, {"id": 15975149, "course_id": 83500, "map_id": 835, "map_name": "kz_symmetry", "map_stage": 0, "stage_tier": 2, "steam_id": "STEAM_1:1:207524905", "player_name": "\u6162\u6162", "mode": "kz_timer", "time": 386.527, "teleports": 0, "created_on": "2022-04-07T04:29:15Z", "points": 7117}, {"id": 22241272, "course_id": 83500, "map_id": 835, "map_name": "kz_symmetry", "map_stage": 0, "stage_tier": 2, "steam_id": "STEAM_1:1:53711411", "player_name": "GiantStorm", "mode": "kz_timer", "time": 386.859, "teleports": 0, "created_on": "2023-07-16T22:52:42Z", "points": 7114}, {"id": 10702949, "course_id": 83500, "map_id": 835, "map_name": "kz_symmetry", "map_stage": 0, "stage_tier": 2, "steam_id": "STEAM_1:0:100919806", "player_name": "gats (no lid) aka. Throb Dyrdek", "mode": "kz_timer", "time": 388.563, "teleports": 0, "created_on": "2021-02-21T15:28:30Z", "points": 7098}, {"id": 8035705, "course_id": 83500, "map_id": 835, "map_name": "kz_symmetry", "map_stage": 0, "stage_tier": 2, "steam_id": "STEAM_1:0:194329783", "player_name": "Flex-jz", "mode": "kz_timer", "time": 397.986, "teleports": 0, "created_on": "2020-09-08T11:26:47Z", "points": 7011}, {"id": 8032567, "course_id": 83500, "map_id": 835, "map_name": "kz_symmetry", "map_stage": 0, "stage_tier": 2, "steam_id": "STEAM_1:1:56170518", "player_name": "nooobydoobynoob", "mode": "kz_timer", "time": 400.195, "teleports": 0, "created_on": "2020-09-08T06:40:14Z", "points": 6989}, {"id": 8184297, "course_id": 83500, "map_id": 835, "map_name": "kz_symmetry", "map_stage": 0, "stage_tier": 2, "steam_id": "STEAM_1:0:14119390", "player_name": "CLear`", "mode": "kz_timer", "time": 408.641, "teleports": 0, "created_on": "2020-09-17T11:55:32Z", "points": 6909}, {"id": 11361100, "course_id": 83500, "map_id": 835, "map_name": "kz_symmetry", "map_stage": 0, "stage_tier": 2, "steam_id": "STEAM_1:1:109488339", "player_name": "Ayanokouji", "mode": "kz_timer", "time": 408.883, "teleports": 0, "created_on": "2021-03-28T11:06:23Z", "points": 6906}, {"id": 19670610, "course_id": 83500, "map_id": 835, "map_name": "kz_symmetry", "map_stage": 0, "stage_tier": 2, "steam_id": "STEAM_1:0:588897328", "player_name": "zuzubear", "mode": "kz_timer", "time": 409.484, "teleports": 0, "created_on": "2023-01-22T01:35:54Z", "points": 6901}, {"id": 8025551, "course_id": 83500, "map_id": 835, "map_name": "kz_symmetry", "map_stage": 0, "stage_tier": 2, "steam_id": "STEAM_1:0:200965086", "player_name": "epicpfeffer", "mode": "kz_timer", "time": 410.719, "teleports": 0, "created_on": "2020-09-07T22:08:26Z", "points": 6889}, {"id": 11010503, "course_id": 83500, "map_id": 835, "map_name": "kz_symmetry", "map_stage": 0, "stage_tier": 2, "steam_id": "STEAM_1:0:60172599", "player_name": "Zoraketh", "mode": "kz_timer", "time": 412.508, "teleports": 0, "created_on": "2021-03-09T22:23:57Z", "points": 6871}, {"id": 11577859, "course_id": 83500, "map_id": 835, "map_name": "kz_symmetry", "map_stage": 0, "stage_tier": 2, "steam_id": "STEAM_1:1:17849866", "player_name": "YouM3 <CS2 Enjoyer>", "mode": "kz_timer", "time": 420.328, "teleports": 0, "created_on": "2021-04-09T07:46:44Z", "points": 6793}, {"id": 20546726, "course_id": 83500, "map_id": 835, "map_name": "kz_symmetry", "map_stage": 0, "stage_tier": 2, "steam_id": "STEAM_1:0:704369093", "player_name": "vadacleler82", "mode": "kz_timer", "time": 420.586, "teleports": 0, "created_on": "2023-04-03T21:01:36Z", "points": 6791}, {"id": 11382059, "course_id": 83500, "map_id": 835, "map_name": "kz_symmetry", "map_stage": 0, "stage_tier": 2, "steam_id": "STEAM_1:0:422663348", "player_name": "drama", "mode": "kz_timer", "time": 432.25, "teleports": 0, "created_on": "2021-03-29T14:44:48Z", "points": 6678}, {"id": 22902531, "course_id": 83500, "map_id": 835, "map_name": "kz_symmetry", "map_stage": 0, "stage_tier": 2, "steam_id": "STEAM_1:0:146494308", "player_name": "\u963f\u7f8a", "mode": "kz_timer", "time": 437.906, "teleports": 0, "created_on": "2023-08-30T12:05:08Z", "points": 6621}, {"id": 8028836, "course_id": 83500, "map_id": 835, "map_name": "kz_symmetry", "map_stage": 0, "stage_tier": 2, "steam_id": "STEAM_1:1:210646321", "player_name": "Garysniffs", "mode": "kz_timer", "time": 443.906, "teleports": 0, "created_on": "2020-09-08T01:45:56Z", "points": 6561}, {"id": 17681587, "course_id": 83500, "map_id": 835, "map_name": "kz_symmetry", "map_stage": 0, "stage_tier": 2, "steam_id": "STEAM_1:1:38365989", "player_name": "satan", "mode": "kz_timer", "time": 447.129, "teleports": 0, "created_on": "2022-08-16T03:07:26Z", "points": 6531}, {"id": 14169909, "course_id": 83500, "map_id": 835, "map_name": "kz_symmetry", "map_stage": 0, "stage_tier": 2, "steam_id": "STEAM_1:1:84791641", "player_name": "Scythe", "mode": "kz_timer", "time": 447.891, "teleports": 0, "created_on": "2021-10-31T06:28:00Z", "points": 6523}, {"id": 8022364, "course_id": 83500, "map_id": 835, "map_name": "kz_symmetry", "map_stage": 0, "stage_tier": 2, "steam_id": "STEAM_1:0:86429878", "player_name": "BigMitch128", "mode": "kz_timer", "time": 452.352, "teleports": 0, "created_on": "2020-09-07T19:17:42Z", "points": 6479}, {"id": 16435172, "course_id": 83500, "map_id": 835, "map_name": "kz_symmetry", "map_stage": 0, "stage_tier": 2, "steam_id": "STEAM_1:0:53440872", "player_name": "flurreh:>", "mode": "kz_timer", "time": 460.047, "teleports": 0, "created_on": "2022-05-12T18:47:28Z", "points": 6406}, {"id": 13989649, "course_id": 83500, "map_id": 835, "map_name": "kz_symmetry", "map_stage": 0, "stage_tier": 2, "steam_id": "STEAM_1:1:154511136", "player_name": "10hz", "mode": "kz_timer", "time": 462.555, "teleports": 0, "created_on": "2021-10-13T00:00:45Z", "points": 6380}, {"id": 8388387, "course_id": 83500, "map_id": 835, "map_name": "kz_symmetry", "map_stage": 0, "stage_tier": 2, "steam_id": "STEAM_1:1:9836467", "player_name": "Charon", "mode": "kz_timer", "time": 465.086, "teleports": 0, "created_on": "2020-10-01T03:40:33Z", "points": 6355}, {"id": 11743323, "course_id": 83500, "map_id": 835, "map_name": "kz_symmetry", "map_stage": 0, "stage_tier": 2, "steam_id": "STEAM_1:0:19273898", "player_name": "bob", "mode": "kz_timer", "time": 466.875, "teleports": 0, "created_on": "2021-04-18T02:48:09Z", "points": 6338}, {"id": 21403315, "course_id": 83500, "map_id": 835, "map_name": "kz_symmetry", "map_stage": 0, "stage_tier": 2, "steam_id": "STEAM_1:1:458881112", "player_name": "Pizza delivery for u", "mode": "kz_timer", "time": 477.418, "teleports": 0, "created_on": "2023-05-24T14:55:59Z", "points": 6236}, {"id": 17539944, "course_id": 83500, "map_id": 835, "map_name": "kz_symmetry", "map_stage": 0, "stage_tier": 2, "steam_id": "STEAM_1:0:28667243", "player_name": "KAPA", "mode": "kz_timer", "time": 478.0, "teleports": 0, "created_on": "2022-08-07T01:26:24Z", "points": 6231}, {"id": 12199707, "course_id": 83500, "map_id": 835, "map_name": "kz_symmetry", "map_stage": 0, "stage_tier": 2, "steam_id": "STEAM_1:1:96418204", "player_name": "AetherCG", "mode": "kz_timer", "time": 482.547, "teleports": 0, "created_on": "2021-05-15T00:35:21Z", "points": 6187}, {"id": 22057817, "course_id": 83500, "map_id": 835, "map_name": "kz_symmetry", "map_stage": 0, "stage_tier": 2, "steam_id": "STEAM_1:0:543497135", "player_name": "ArcticFox", "mode": "kz_timer", "time": 495.672, "teleports": 0, "created_on": "2023-07-04T13:39:00Z", "points": 6054}, {"id": 9592777, "course_id": 83500, "map_id": 835, "map_name": "kz_symmetry", "map_stage": 0, "stage_tier": 2, "steam_id": "STEAM_1:0:115193683", "player_name": "jinglepuff", "mode": "kz_timer", "time": 500.852, "teleports": 0, "created_on": "2020-12-21T21:38:36Z", "points": 6002}, {"id": 11869488, "course_id": 83500, "map_id": 835, "map_name": "kz_symmetry", "map_stage": 0, "stage_tier": 2, "steam_id": "STEAM_1:0:85436699", "player_name": "\u00bf", "mode": "kz_timer", "time": 509.008, "teleports": 0, "created_on": "2021-04-25T09:32:11Z", "points": 5922}, {"id": 20613366, "course_id": 83500, "map_id": 835, "map_name": "kz_symmetry", "map_stage": 0, "stage_tier": 2, "steam_id": "STEAM_1:1:42047729", "player_name": "AlneS", "mode": "kz_timer", "time": 510.867, "teleports": 0, "created_on": "2023-04-07T08:10:22Z", "points": 5902}, {"id": 14706736, "course_id": 83500, "map_id": 835, "map_name": "kz_symmetry", "map_stage": 0, "stage_tier": 2, "steam_id": "STEAM_1:0:92924671", "player_name": "Gary", "mode": "kz_timer", "time": 512.5, "teleports": 0, "created_on": "2021-12-22T18:25:15Z", "points": 5884}, {"id": 10413444, "course_id": 83500, "map_id": 835, "map_name": "kz_symmetry", "map_stage": 0, "stage_tier": 2, "steam_id": "STEAM_1:1:231784845", "player_name": "hehe", "mode": "kz_timer", "time": 527.625, "teleports": 0, "created_on": "2021-02-06T01:38:22Z", "points": 5735}, {"id": 13796736, "course_id": 83500, "map_id": 835, "map_name": "kz_symmetry", "map_stage": 0, "stage_tier": 2, "steam_id": "STEAM_1:0:76767687", "player_name": "booboo47", "mode": "kz_timer", "time": 532.1, "teleports": 0, "created_on": "2021-09-24T04:19:43Z", "points": 5691}, {"id": 8026763, "course_id": 83500, "map_id": 835, "map_name": "kz_symmetry", "map_stage": 0, "stage_tier": 2, "steam_id": "STEAM_1:1:59506737", "player_name": "tumppi", "mode": "kz_timer", "time": 533.047, "teleports": 0, "created_on": "2020-09-07T23:30:55Z", "points": 5682}, {"id": 19567135, "course_id": 83500, "map_id": 835, "map_name": "kz_symmetry", "map_stage": 0, "stage_tier": 2, "steam_id": "STEAM_1:1:242991692", "player_name": "Yung Blyatt", "mode": "kz_timer", "time": 538.148, "teleports": 0, "created_on": "2023-01-11T18:07:38Z", "points": 5633}, {"id": 15895679, "course_id": 83500, "map_id": 835, "map_name": "kz_symmetry", "map_stage": 0, "stage_tier": 2, "steam_id": "STEAM_1:1:210249835", "player_name": "/\\0h(", "mode": "kz_timer", "time": 544.695, "teleports": 0, "created_on": "2022-03-31T02:51:30Z", "points": 5568}, {"id": 22808881, "course_id": 83500, "map_id": 835, "map_name": "kz_symmetry", "map_stage": 0, "stage_tier": 2, "steam_id": "STEAM_1:1:561935794", "player_name": "unmotivated.", "mode": "kz_timer", "time": 551.156, "teleports": 0, "created_on": "2023-08-24T09:01:14Z", "points": 5505}, {"id": 11794661, "course_id": 83500, "map_id": 835, "map_name": "kz_symmetry", "map_stage": 0, "stage_tier": 2, "steam_id": "STEAM_1:1:53724650", "player_name": "Friend", "mode": "kz_timer", "time": 563.934, "teleports": 0, "created_on": "2021-04-21T00:02:22Z", "points": 5384}, {"id": 9351822, "course_id": 83500, "map_id": 835, "map_name": "kz_symmetry", "map_stage": 0, "stage_tier": 2, "steam_id": "STEAM_1:0:20776017", "player_name": "hello", "mode": "kz_timer", "time": 571.195, "teleports": 0, "created_on": "2020-12-06T20:58:36Z", "points": 5315}, {"id": 9194764, "course_id": 83500, "map_id": 835, "map_name": "kz_symmetry", "map_stage": 0, "stage_tier": 2, "steam_id": "STEAM_1:0:61409313", "player_name": "DeKo", "mode": "kz_timer", "time": 577.625, "teleports": 0, "created_on": "2020-11-26T18:38:11Z", "points": 5253}, {"id": 14941186, "course_id": 83500, "map_id": 835, "map_name": "kz_symmetry", "map_stage": 0, "stage_tier": 2, "steam_id": "STEAM_1:1:148954384", "player_name": "picard", "mode": "kz_timer", "time": 582.094, "teleports": 0, "created_on": "2022-01-13T13:33:16Z", "points": 5211}, {"id": 8677939, "course_id": 83500, "map_id": 835, "map_name": "kz_symmetry", "map_stage": 0, "stage_tier": 2, "steam_id": "STEAM_1:0:197589755", "player_name": "Jim", "mode": "kz_timer", "time": 583.99, "teleports": 0, "created_on": "2020-10-22T00:41:47Z", "points": 5193}, {"id": 16345247, "course_id": 83500, "map_id": 835, "map_name": "kz_symmetry", "map_stage": 0, "stage_tier": 2, "steam_id": "STEAM_1:0:556103746", "player_name": "Macho", "mode": "kz_timer", "time": 608.742, "teleports": 0, "created_on": "2022-05-06T01:14:05Z", "points": 4965}, {"id": 9851538, "course_id": 83500, "map_id": 835, "map_name": "kz_symmetry", "map_stage": 0, "stage_tier": 2, "steam_id": "STEAM_1:1:199149464", "player_name": "wend1go \u2661", "mode": "kz_timer", "time": 614.297, "teleports": 0, "created_on": "2021-01-06T10:37:45Z", "points": 4915}, {"id": 11243812, "course_id": 83500, "map_id": 835, "map_name": "kz_symmetry", "map_stage": 0, "stage_tier": 2, "steam_id": "STEAM_1:0:190170666", "player_name": "Mur", "mode": "kz_timer", "time": 624.715, "teleports": 0, "created_on": "2021-03-22T08:48:52Z", "points": 4821}, {"id": 9498802, "course_id": 83500, "map_id": 835, "map_name": "kz_symmetry", "map_stage": 0, "stage_tier": 2, "steam_id": "STEAM_1:1:511092302", "player_name": "Silviet_", "mode": "kz_timer", "time": 635.063, "teleports": 0, "created_on": "2020-12-16T10:19:11Z", "points": 4727}, {"id": 11297307, "course_id": 83500, "map_id": 835, "map_name": "kz_symmetry", "map_stage": 0, "stage_tier": 2, "steam_id": "STEAM_1:0:197786587", "player_name": "ABASHED", "mode": "kz_timer", "time": 636.531, "teleports": 0, "created_on": "2021-03-25T04:01:26Z", "points": 4715}, {"id": 8032250, "course_id": 83500, "map_id": 835, "map_name": "kz_symmetry", "map_stage": 0, "stage_tier": 2, "steam_id": "STEAM_1:0:40962357", "player_name": "Ice", "mode": "kz_timer", "time": 640.625, "teleports": 0, "created_on": "2020-09-08T06:12:03Z", "points": 4677}, {"id": 21032156, "course_id": 83500, "map_id": 835, "map_name": "kz_symmetry", "map_stage": 0, "stage_tier": 2, "steam_id": "STEAM_1:0:185002974", "player_name": "Luffy", "mode": "kz_timer", "time": 647.297, "teleports": 0, "created_on": "2023-04-29T03:19:32Z", "points": 4618}, {"id": 21736566, "course_id": 83500, "map_id": 835, "map_name": "kz_symmetry", "map_stage": 0, "stage_tier": 2, "steam_id": "STEAM_1:0:448851726", "player_name": "f e l i x", "mode": "kz_timer", "time": 654.328, "teleports": 0, "created_on": "2023-06-12T19:34:56Z", "points": 4556}, {"id": 12370610, "course_id": 83500, "map_id": 835, "map_name": "kz_symmetry", "map_stage": 0, "stage_tier": 2, "steam_id": "STEAM_1:0:156722303", "player_name": "Aimer", "mode": "kz_timer", "time": 671.875, "teleports": 0, "created_on": "2021-05-26T07:53:46Z", "points": 4400}, {"id": 16345265, "course_id": 83500, "map_id": 835, "map_name": "kz_symmetry", "map_stage": 0, "stage_tier": 2, "steam_id": "STEAM_1:1:191889352", "player_name": "TinyGreenDino", "mode": "kz_timer", "time": 678.391, "teleports": 0, "created_on": "2022-05-06T01:18:44Z", "points": 4345}, {"id": 15797315, "course_id": 83500, "map_id": 835, "map_name": "kz_symmetry", "map_stage": 0, "stage_tier": 2, "steam_id": "STEAM_1:0:567486742", "player_name": "lasci", "mode": "kz_timer", "time": 679.665, "teleports": 0, "created_on": "2022-03-22T06:16:14Z", "points": 4335}, {"id": 12308453, "course_id": 83500, "map_id": 835, "map_name": "kz_symmetry", "map_stage": 0, "stage_tier": 2, "steam_id": "STEAM_1:1:516543", "player_name": "KakanV", "mode": "kz_timer", "time": 684.289, "teleports": 0, "created_on": "2021-05-21T19:47:06Z", "points": 4298}, {"id": 15880193, "course_id": 83500, "map_id": 835, "map_name": "kz_symmetry", "map_stage": 0, "stage_tier": 2, "steam_id": "STEAM_1:1:42464342", "player_name": "Slippy", "mode": "kz_timer", "time": 685.53, "teleports": 0, "created_on": "2022-03-29T14:33:51Z", "points": 4287}, {"id": 14388531, "course_id": 83500, "map_id": 835, "map_name": "kz_symmetry", "map_stage": 0, "stage_tier": 2, "steam_id": "STEAM_1:1:96786116", "player_name": "Infinite", "mode": "kz_timer", "time": 733.266, "teleports": 0, "created_on": "2021-11-22T15:11:09Z", "points": 3907}, {"id": 11812229, "course_id": 83500, "map_id": 835, "map_name": "kz_symmetry", "map_stage": 0, "stage_tier": 2, "steam_id": "STEAM_1:1:23798951", "player_name": "Jnas Cage", "mode": "kz_timer", "time": 747.508, "teleports": 0, "created_on": "2021-04-21T23:47:49Z", "points": 3798}, {"id": 15105262, "course_id": 83500, "map_id": 835, "map_name": "kz_symmetry", "map_stage": 0, "stage_tier": 2, "steam_id": "STEAM_1:1:165530312", "player_name": "Aava", "mode": "kz_timer", "time": 748.688, "teleports": 0, "created_on": "2022-01-26T20:57:50Z", "points": 3789}, {"id": 8027656, "course_id": 83500, "map_id": 835, "map_name": "kz_symmetry", "map_stage": 0, "stage_tier": 2, "steam_id": "STEAM_1:0:47706744", "player_name": "radioaktiv", "mode": "kz_timer", "time": 749.322, "teleports": 0, "created_on": "2020-09-08T00:26:21Z", "points": 3784}, {"id": 14934681, "course_id": 83500, "map_id": 835, "map_name": "kz_symmetry", "map_stage": 0, "stage_tier": 2, "steam_id": "STEAM_1:1:49613455", "player_name": "I love Swat <3", "mode": "kz_timer", "time": 753.43, "teleports": 0, "created_on": "2022-01-12T21:54:50Z", "points": 3752}, {"id": 11630374, "course_id": 83500, "map_id": 835, "map_name": "kz_symmetry", "map_stage": 0, "stage_tier": 2, "steam_id": "STEAM_1:0:105247603", "player_name": "NightBlade", "mode": "kz_timer", "time": 760.672, "teleports": 0, "created_on": "2021-04-11T20:08:08Z", "points": 3698}, {"id": 20293049, "course_id": 83500, "map_id": 835, "map_name": "kz_symmetry", "map_stage": 0, "stage_tier": 2, "steam_id": "STEAM_1:1:21795425", "player_name": "Heros5k #ClashGG", "mode": "kz_timer", "time": 777.617, "teleports": 0, "created_on": "2023-03-21T01:19:01Z", "points": 3576}, {"id": 13318730, "course_id": 83500, "map_id": 835, "map_name": "kz_symmetry", "map_stage": 0, "stage_tier": 2, "steam_id": "STEAM_1:1:84064410", "player_name": "Al0ne", "mode": "kz_timer", "time": 791.545, "teleports": 0, "created_on": "2021-08-13T21:10:24Z", "points": 3477}, {"id": 11902403, "course_id": 83500, "map_id": 835, "map_name": "kz_symmetry", "map_stage": 0, "stage_tier": 2, "steam_id": "STEAM_1:1:3942875", "player_name": "Mikko", "mode": "kz_timer", "time": 805.383, "teleports": 0, "created_on": "2021-04-27T08:22:34Z", "points": 3382}, {"id": 8087027, "course_id": 83500, "map_id": 835, "map_name": "kz_symmetry", "map_stage": 0, "stage_tier": 2, "steam_id": "STEAM_1:0:164426699", "player_name": "Jebe", "mode": "kz_timer", "time": 809.133, "teleports": 0, "created_on": "2020-09-11T11:04:50Z", "points": 3355}, {"id": 11880299, "course_id": 83500, "map_id": 835, "map_name": "kz_symmetry", "map_stage": 0, "stage_tier": 2, "steam_id": "STEAM_1:1:96265422", "player_name": "*999", "mode": "kz_timer", "time": 849.508, "teleports": 0, "created_on": "2021-04-25T21:44:47Z", "points": 3094}, {"id": 11728007, "course_id": 83500, "map_id": 835, "map_name": "kz_symmetry", "map_stage": 0, "stage_tier": 2, "steam_id": "STEAM_1:1:18886549", "player_name": "OSUMA", "mode": "kz_timer", "time": 895.438, "teleports": 0, "created_on": "2021-04-17T07:20:23Z", "points": 2824}, {"id": 21828675, "course_id": 83500, "map_id": 835, "map_name": "kz_symmetry", "map_stage": 0, "stage_tier": 2, "steam_id": "STEAM_1:0:42620969", "player_name": "ajni", "mode": "kz_timer", "time": 916.813, "teleports": 0, "created_on": "2023-06-18T09:38:13Z", "points": 2705}, {"id": 18489600, "course_id": 83500, "map_id": 835, "map_name": "kz_symmetry", "map_stage": 0, "stage_tier": 2, "steam_id": "STEAM_1:1:633453176", "player_name": "\u67da\u5b50_:3", "mode": "kz_timer", "time": 935.492, "teleports": 0, "created_on": "2022-10-12T10:58:27Z", "points": 2606}, {"id": 11680316, "course_id": 83500, "map_id": 835, "map_name": "kz_symmetry", "map_stage": 0, "stage_tier": 2, "steam_id": "STEAM_1:1:452664577", "player_name": "Lil bitchy", "mode": "kz_timer", "time": 947.586, "teleports": 0, "created_on": "2021-04-14T15:38:21Z", "points": 2542}, {"id": 18891753, "course_id": 83500, "map_id": 835, "map_name": "kz_symmetry", "map_stage": 0, "stage_tier": 2, "steam_id": "STEAM_1:0:191856662", "player_name": "Sh1nigami", "mode": "kz_timer", "time": 961.141, "teleports": 0, "created_on": "2022-11-12T13:54:28Z", "points": 2476}, {"id": 19777541, "course_id": 83500, "map_id": 835, "map_name": "kz_symmetry", "map_stage": 0, "stage_tier": 2, "steam_id": "STEAM_1:0:523441903", "player_name": "\u785d\u785d\u785d\u785d\u785d\u785d\u785d\u785d\u785d\u5b50", "mode": "kz_timer", "time": 1039.984, "teleports": 0, "created_on": "2023-01-31T09:39:06Z", "points": 2122}, {"id": 18135723, "course_id": 83500, "map_id": 835, "map_name": "kz_symmetry", "map_stage": 0, "stage_tier": 2, "steam_id": "STEAM_1:1:92712277", "player_name": "Fara", "mode": "kz_timer", "time": 1049.805, "teleports": 0, "created_on": "2022-09-16T13:16:26Z", "points": 2081}, {"id": 11727896, "course_id": 83500, "map_id": 835, "map_name": "kz_symmetry", "map_stage": 0, "stage_tier": 2, "steam_id": "STEAM_1:1:18239482", "player_name": "Hans-J\u00fcrgen von Arnim", "mode": "kz_timer", "time": 1061.063, "teleports": 0, "created_on": "2021-04-17T07:02:54Z", "points": 2036}, {"id": 21390522, "course_id": 83500, "map_id": 835, "map_name": "kz_symmetry", "map_stage": 0, "stage_tier": 2, "steam_id": "STEAM_1:0:518226995", "player_name": "bat shit crazy insane gamer", "mode": "kz_timer", "time": 1346.211, "teleports": 0, "created_on": "2023-05-23T16:23:35Z", "points": 1622}, {"id": 8038622, "course_id": 83500, "map_id": 835, "map_name": "kz_symmetry", "map_stage": 0, "stage_tier": 2, "steam_id": "STEAM_1:1:14631876", "player_name": "AktiveSterbehilfe", "mode": "kz_timer", "time": 1407.281, "teleports": 0, "created_on": "2020-09-08T14:50:52Z", "points": 1598}, {"id": 8024935, "course_id": 83500, "map_id": 835, "map_name": "kz_symmetry", "map_stage": 0, "stage_tier": 2, "steam_id": "STEAM_1:1:164726559", "player_name": "Floppy", "mode": "kz_timer", "time": 1445.016, "teleports": 0, "created_on": "2020-09-07T21:30:09Z", "points": 1583}, {"id": 17489663, "course_id": 83500, "map_id": 835, "map_name": "kz_symmetry", "map_stage": 0, "stage_tier": 2, "steam_id": "STEAM_1:0:44770837", "player_name": "topyo", "mode": "kz_timer", "time": 1495.57, "teleports": 0, "created_on": "2022-08-03T16:21:36Z", "points": 1566}, {"id": 8866268, "course_id": 83500, "map_id": 835, "map_name": "kz_symmetry", "map_stage": 0, "stage_tier": 2, "steam_id": "STEAM_1:0:2105250", "player_name": "gangien", "mode": "kz_timer", "time": 1579.93, "teleports": 0, "created_on": "2020-11-03T22:35:26Z", "points": 1544}, {"id": 9158263, "course_id": 83500, "map_id": 835, "map_name": "kz_symmetry", "map_stage": 0, "stage_tier": 2, "steam_id": "STEAM_1:0:47245762", "player_name": "Nyong", "mode": "kz_timer", "time": 1582.828, "teleports": 0, "created_on": "2020-11-24T10:00:19Z", "points": 1538}, {"id": 8119314, "course_id": 83500, "map_id": 835, "map_name": "kz_symmetry", "map_stage": 0, "stage_tier": 2, "steam_id": "STEAM_1:1:104358191", "player_name": "\u8239\u898b\u7d50\u8863", "mode": "kz_timer", "time": 1866.383, "teleports": 0, "created_on": "2020-09-13T07:31:55Z", "points": 1497}, {"id": 18268706, "course_id": 83500, "map_id": 835, "map_name": "kz_symmetry", "map_stage": 0, "stage_tier": 2, "steam_id": "STEAM_1:0:510286924", "player_name": "ArcticFox", "mode": "kz_timer", "time": 2074.938, "teleports": 0, "created_on": "2022-09-25T08:15:18Z", "points": 1478}]